[
  {"state" : "IN",
    "zip": "47906",
    "city": "West Lafayette",
    "county": "Tippecanoe",
    "pop": 77702
  },
  {"state" : "IN",
    "zip": "46307",
    "city": "Crown Point",
    "county": "Lake",
    "pop": 62779
  },
  {"state" : "IN",
    "zip": "46143",
    "city": "Greenwood",
    "county": "Johnson",
    "pop": 57211
  },
  {"state" : "IN",
    "zip": "46227",
    "city": "Indianapolis",
    "county": "Marion",
    "pop": 54876
  },
  {"state" : "IN",
    "zip": "46032",
    "city": "Carmel",
    "county": "Hamilton",
    "pop": 51551
  },
  {"state" : "IN",
    "zip": "47150",
    "city": "New Albany",
    "county": "Floyd",
    "pop": 47912
  },
  {"state" : "IN",
    "zip": "47130",
    "city": "Jeffersonville",
    "county": "Clark",
    "pop": 46645
  },
  {"state" : "IN",
    "zip": "46226",
    "city": "Indianapolis",
    "county": "Marion",
    "pop": 45652
  },
  {"state" : "IN",
    "zip": "47374",
    "city": "Richmond",
    "county": "Wayne",
    "pop": 45571
  },
  {"state" : "IN",
    "zip": "47201",
    "city": "Columbus",
    "county": "Bartholomew",
    "pop": 44831
  },
  {"state" : "IN",
    "zip": "46360",
    "city": "Michigan City",
    "county": "La Porte",
    "pop": 43678
  },
  {"state" : "IN",
    "zip": "46038",
    "city": "Fishers",
    "county": "Hamilton",
    "pop": 43381
  },
  {"state" : "IN",
    "zip": "47909",
    "city": "Lafayette",
    "county": "Tippecanoe",
    "pop": 43291
  },
  {"state" : "IN",
    "zip": "47401",
    "city": "Bloomington",
    "county": "Monroe",
    "pop": 43279
  },
  {"state" : "IN",
    "zip": "46350",
    "city": "La Porte",
    "county": "La Porte",
    "pop": 42763
  },
  {"state" : "IN",
    "zip": "46383",
    "city": "Valparaiso",
    "county": "Porter",
    "pop": 42245
  },
  {"state" : "IN",
    "zip": "47905",
    "city": "Lafayette",
    "county": "Tippecanoe",
    "pop": 41631
  },
  {"state" : "IN",
    "zip": "46514",
    "city": "Elkhart",
    "county": "Elkhart",
    "pop": 41616
  },
  {"state" : "IN",
    "zip": "46060",
    "city": "Noblesville",
    "county": "Hamilton",
    "pop": 41461
  },
  {"state" : "IN",
    "zip": "46140",
    "city": "Greenfield",
    "county": "Hancock",
    "pop": 40292
  },
  {"state" : "IN",
    "zip": "46254",
    "city": "Indianapolis",
    "county": "Marion",
    "pop": 40276
  },
  {"state" : "IN",
    "zip": "46385",
    "city": "Valparaiso",
    "county": "Porter",
    "pop": 39398
  },
  {"state" : "IN",
    "zip": "46901",
    "city": "Kokomo",
    "county": "Howard",
    "pop": 39383
  },
  {"state" : "IN",
    "zip": "46237",
    "city": "Indianapolis",
    "county": "Marion",
    "pop": 39169
  },
  {"state" : "IN",
    "zip": "46033",
    "city": "Carmel",
    "county": "Hamilton",
    "pop": 38942
  },
  {"state" : "IN",
    "zip": "46368",
    "city": "Portage",
    "county": "Porter",
    "pop": 38661
  },
  {"state" : "IN",
    "zip": "46203",
    "city": "Indianapolis",
    "county": "Marion",
    "pop": 38581
  },
  {"state" : "IN",
    "zip": "46222",
    "city": "Indianapolis",
    "county": "Marion",
    "pop": 37885
  },
  {"state" : "IN",
    "zip": "46112",
    "city": "Brownsburg",
    "county": "Hendricks",
    "pop": 37819
  },
  {"state" : "IN",
    "zip": "46410",
    "city": "Merrillville",
    "county": "Lake",
    "pop": 37813
  },
  {"state" : "IN",
    "zip": "46224",
    "city": "Indianapolis",
    "county": "Marion",
    "pop": 37074
  },
  {"state" : "IN",
    "zip": "46219",
    "city": "Indianapolis",
    "county": "Marion",
    "pop": 36940
  },
  {"state" : "IN",
    "zip": "46217",
    "city": "Indianapolis",
    "county": "Marion",
    "pop": 36843
  },
  {"state" : "IN",
    "zip": "46123",
    "city": "Avon",
    "county": "Hendricks",
    "pop": 36616
  },
  {"state" : "IN",
    "zip": "46220",
    "city": "Indianapolis",
    "county": "Marion",
    "pop": 36585
  },
  {"state" : "IN",
    "zip": "47630",
    "city": "Newburgh",
    "county": "Warrick",
    "pop": 36182
  },
  {"state" : "IN",
    "zip": "46902",
    "city": "Kokomo",
    "county": "Howard",
    "pop": 35778
  },
  {"state" : "IN",
    "zip": "46835",
    "city": "Fort Wayne",
    "county": "Allen",
    "pop": 35658
  },
  {"state" : "IN",
    "zip": "46168",
    "city": "Plainfield",
    "county": "Hendricks",
    "pop": 35418
  },
  {"state" : "IN",
    "zip": "47802",
    "city": "Terre Haute",
    "county": "Vigo",
    "pop": 34894
  },
  {"state" : "IN",
    "zip": "46074",
    "city": "Westfield",
    "county": "Hamilton",
    "pop": 34755
  },
  {"state" : "IN",
    "zip": "47714",
    "city": "Evansville",
    "county": "Vanderburgh",
    "pop": 34447
  },
  {"state" : "IN",
    "zip": "46260",
    "city": "Indianapolis",
    "county": "Marion",
    "pop": 34445
  },
  {"state" : "IN",
    "zip": "47403",
    "city": "Bloomington",
    "county": "Monroe",
    "pop": 33505
  },
  {"state" : "IN",
    "zip": "46131",
    "city": "Franklin",
    "county": "Johnson",
    "pop": 33215
  },
  {"state" : "IN",
    "zip": "46526",
    "city": "Goshen",
    "county": "Elkhart",
    "pop": 33117
  },
  {"state" : "IN",
    "zip": "46235",
    "city": "Indianapolis",
    "county": "Marion",
    "pop": 33063
  },
  {"state" : "IN",
    "zip": "47711",
    "city": "Evansville",
    "county": "Vanderburgh",
    "pop": 32612
  },
  {"state" : "IN",
    "zip": "47304",
    "city": "Muncie",
    "county": "Delaware",
    "pop": 32105
  },
  {"state" : "IN",
    "zip": "46544",
    "city": "Mishawaka",
    "county": "St Joseph",
    "pop": 31988
  },
  {"state" : "IN",
    "zip": "46241",
    "city": "Indianapolis",
    "county": "Marion",
    "pop": 31941
  },
  {"state" : "IN",
    "zip": "46530",
    "city": "Granger",
    "county": "St Joseph",
    "pop": 31843
  },
  {"state" : "IN",
    "zip": "46151",
    "city": "Martinsville",
    "county": "Morgan",
    "pop": 31589
  },
  {"state" : "IN",
    "zip": "47274",
    "city": "Seymour",
    "county": "Jackson",
    "pop": 31352
  },
  {"state" : "IN",
    "zip": "46516",
    "city": "Elkhart",
    "county": "Elkhart",
    "pop": 31329
  },
  {"state" : "IN",
    "zip": "46614",
    "city": "South Bend",
    "county": "St Joseph",
    "pop": 31035
  },
  {"state" : "IN",
    "zip": "46201",
    "city": "Indianapolis",
    "county": "Marion",
    "pop": 30962
  },
  {"state" : "IN",
    "zip": "46342",
    "city": "Hobart",
    "county": "Lake",
    "pop": 30874
  },
  {"state" : "IN",
    "zip": "46239",
    "city": "Indianapolis",
    "county": "Marion",
    "pop": 30651
  },
  {"state" : "IN",
    "zip": "47362",
    "city": "New Castle",
    "county": "Henry",
    "pop": 29873
  },
  {"state" : "IN",
    "zip": "46142",
    "city": "Greenwood",
    "county": "Johnson",
    "pop": 29696
  },
  {"state" : "IN",
    "zip": "46825",
    "city": "Fort Wayne",
    "county": "Allen",
    "pop": 29507
  },
  {"state" : "IN",
    "zip": "46077",
    "city": "Zionsville",
    "county": "Boone",
    "pop": 29296
  },
  {"state" : "IN",
    "zip": "46218",
    "city": "Indianapolis",
    "county": "Marion",
    "pop": 28918
  },
  {"state" : "IN",
    "zip": "46229",
    "city": "Indianapolis",
    "county": "Marion",
    "pop": 28768
  },
  {"state" : "IN",
    "zip": "46236",
    "city": "Indianapolis",
    "county": "Marion",
    "pop": 28705
  },
  {"state" : "IN",
    "zip": "46804",
    "city": "Fort Wayne",
    "county": "Allen",
    "pop": 28587
  },
  {"state" : "IN",
    "zip": "46815",
    "city": "Fort Wayne",
    "county": "Allen",
    "pop": 28242
  },
  {"state" : "IN",
    "zip": "46312",
    "city": "East Chicago",
    "county": "Lake",
    "pop": 28201
  },
  {"state" : "IN",
    "zip": "46947",
    "city": "Logansport",
    "county": "Cass",
    "pop": 27830
  },
  {"state" : "IN",
    "zip": "46176",
    "city": "Shelbyville",
    "county": "Shelby",
    "pop": 27737
  },
  {"state" : "IN",
    "zip": "46205",
    "city": "Indianapolis",
    "county": "Marion",
    "pop": 27580
  },
  {"state" : "IN",
    "zip": "47933",
    "city": "Crawfordsville",
    "county": "Montgomery",
    "pop": 27521
  },
  {"state" : "IN",
    "zip": "47421",
    "city": "Bedford",
    "county": "Lawrence",
    "pop": 27417
  },
  {"state" : "IN",
    "zip": "46528",
    "city": "Goshen",
    "county": "Elkhart",
    "pop": 27001
  },
  {"state" : "IN",
    "zip": "46234",
    "city": "Indianapolis",
    "county": "Marion",
    "pop": 26864
  },
  {"state" : "IN",
    "zip": "47203",
    "city": "Columbus",
    "county": "Bartholomew",
    "pop": 26807
  },
  {"state" : "IN",
    "zip": "47712",
    "city": "Evansville",
    "county": "Vanderburgh",
    "pop": 26764
  },
  {"state" : "IN",
    "zip": "46221",
    "city": "Indianapolis",
    "county": "Marion",
    "pop": 26714
  },
  {"state" : "IN",
    "zip": "46750",
    "city": "Huntington",
    "county": "Huntington",
    "pop": 26499
  },
  {"state" : "IN",
    "zip": "46517",
    "city": "Elkhart",
    "county": "Elkhart",
    "pop": 26468
  },
  {"state" : "IN",
    "zip": "46628",
    "city": "South Bend",
    "county": "St Joseph",
    "pop": 26396
  },
  {"state" : "IN",
    "zip": "47715",
    "city": "Evansville",
    "county": "Vanderburgh",
    "pop": 26196
  },
  {"state" : "IN",
    "zip": "47302",
    "city": "Muncie",
    "county": "Delaware",
    "pop": 26018
  },
  {"state" : "IN",
    "zip": "47408",
    "city": "Bloomington",
    "county": "Monroe",
    "pop": 25804
  },
  {"state" : "IN",
    "zip": "46268",
    "city": "Indianapolis",
    "county": "Marion",
    "pop": 25443
  },
  {"state" : "IN",
    "zip": "47591",
    "city": "Vincennes",
    "county": "Knox",
    "pop": 25370
  },
  {"state" : "IN",
    "zip": "46304",
    "city": "Chesterton",
    "county": "Porter",
    "pop": 25351
  },
  {"state" : "IN",
    "zip": "47303",
    "city": "Muncie",
    "county": "Delaware",
    "pop": 25124
  },
  {"state" : "IN",
    "zip": "46806",
    "city": "Fort Wayne",
    "county": "Allen",
    "pop": 24711
  },
  {"state" : "IN",
    "zip": "46545",
    "city": "Mishawaka",
    "county": "St Joseph",
    "pop": 24685
  },
  {"state" : "IN",
    "zip": "46214",
    "city": "Indianapolis",
    "county": "Marion",
    "pop": 24549
  },
  {"state" : "IN",
    "zip": "46256",
    "city": "Indianapolis",
    "county": "Marion",
    "pop": 23837
  },
  {"state" : "IN",
    "zip": "47404",
    "city": "Bloomington",
    "county": "Monroe",
    "pop": 23832
  },
  {"state" : "IN",
    "zip": "46563",
    "city": "Plymouth",
    "county": "Marshall",
    "pop": 23664
  },
  {"state" : "IN",
    "zip": "46375",
    "city": "Schererville",
    "county": "Lake",
    "pop": 23598
  },
  {"state" : "IN",
    "zip": "46970",
    "city": "Peru",
    "county": "Miami",
    "pop": 23499
  },
  {"state" : "IN",
    "zip": "46953",
    "city": "Marion",
    "county": "Grant",
    "pop": 23333
  },
  {"state" : "IN",
    "zip": "46725",
    "city": "Columbia City",
    "county": "Whitley",
    "pop": 23286
  },
  {"state" : "IN",
    "zip": "46158",
    "city": "Mooresville",
    "county": "Morgan",
    "pop": 23152
  },
  {"state" : "IN",
    "zip": "46208",
    "city": "Indianapolis",
    "county": "Marion",
    "pop": 23080
  },
  {"state" : "IN",
    "zip": "46845",
    "city": "Fort Wayne",
    "county": "Allen",
    "pop": 23066
  },
  {"state" : "IN",
    "zip": "47025",
    "city": "Lawrenceburg",
    "county": "Dearborn",
    "pop": 22794
  },
  {"state" : "IN",
    "zip": "46321",
    "city": "Munster",
    "county": "Lake",
    "pop": 22689
  },
  {"state" : "IN",
    "zip": "46322",
    "city": "Highland",
    "county": "Lake",
    "pop": 22581
  },
  {"state" : "IN",
    "zip": "46052",
    "city": "Lebanon",
    "county": "Boone",
    "pop": 22443
  },
  {"state" : "IN",
    "zip": "47331",
    "city": "Connersville",
    "county": "Fayette",
    "pop": 22391
  },
  {"state" : "IN",
    "zip": "46041",
    "city": "Frankfort",
    "county": "Clinton",
    "pop": 22247
  },
  {"state" : "IN",
    "zip": "47250",
    "city": "Madison",
    "county": "Jefferson",
    "pop": 22202
  },
  {"state" : "IN",
    "zip": "46323",
    "city": "Hammond",
    "county": "Lake",
    "pop": 22195
  },
  {"state" : "IN",
    "zip": "46580",
    "city": "Warsaw",
    "county": "Kosciusko",
    "pop": 22013
  },
  {"state" : "IN",
    "zip": "47240",
    "city": "Greensburg",
    "county": "Decatur",
    "pop": 21836
  },
  {"state" : "IN",
    "zip": "46324",
    "city": "Hammond",
    "county": "Lake",
    "pop": 21820
  },
  {"state" : "IN",
    "zip": "46805",
    "city": "Fort Wayne",
    "county": "Allen",
    "pop": 21704
  },
  {"state" : "IN",
    "zip": "46311",
    "city": "Dyer",
    "county": "Lake",
    "pop": 21632
  },
  {"state" : "IN",
    "zip": "47546",
    "city": "Jasper",
    "county": "Dubois",
    "pop": 21538
  },
  {"state" : "IN",
    "zip": "46619",
    "city": "South Bend",
    "county": "St Joseph",
    "pop": 21471
  },
  {"state" : "IN",
    "zip": "47803",
    "city": "Terre Haute",
    "county": "Vigo",
    "pop": 20939
  },
  {"state" : "IN",
    "zip": "46818",
    "city": "Fort Wayne",
    "county": "Allen",
    "pop": 20852
  },
  {"state" : "IN",
    "zip": "46202",
    "city": "Indianapolis",
    "county": "Marion",
    "pop": 20504
  },
  {"state" : "IN",
    "zip": "46135",
    "city": "Greencastle",
    "county": "Putnam",
    "pop": 20462
  },
  {"state" : "IN",
    "zip": "47265",
    "city": "North Vernon",
    "county": "Jennings",
    "pop": 20344
  },
  {"state" : "IN",
    "zip": "46808",
    "city": "Fort Wayne",
    "county": "Allen",
    "pop": 19831
  },
  {"state" : "IN",
    "zip": "46012",
    "city": "Anderson",
    "county": "Madison",
    "pop": 19806
  },
  {"state" : "IN",
    "zip": "46240",
    "city": "Indianapolis",
    "county": "Marion",
    "pop": 19785
  },
  {"state" : "IN",
    "zip": "47129",
    "city": "Clarksville",
    "county": "Clark",
    "pop": 19684
  },
  {"state" : "IN",
    "zip": "47834",
    "city": "Brazil",
    "county": "Clay",
    "pop": 19263
  },
  {"state" : "IN",
    "zip": "46816",
    "city": "Fort Wayne",
    "county": "Allen",
    "pop": 19055
  },
  {"state" : "IN",
    "zip": "46733",
    "city": "Decatur",
    "county": "Adams",
    "pop": 18943
  },
  {"state" : "IN",
    "zip": "47710",
    "city": "Evansville",
    "county": "Vanderburgh",
    "pop": 18869
  },
  {"state" : "IN",
    "zip": "46706",
    "city": "Auburn",
    "county": "De Kalb",
    "pop": 18771
  },
  {"state" : "IN",
    "zip": "46952",
    "city": "Marion",
    "county": "Grant",
    "pop": 18625
  },
  {"state" : "IN",
    "zip": "46250",
    "city": "Indianapolis",
    "county": "Marion",
    "pop": 18402
  },
  {"state" : "IN",
    "zip": "46703",
    "city": "Angola",
    "county": "Steuben",
    "pop": 18264
  },
  {"state" : "IN",
    "zip": "46016",
    "city": "Anderson",
    "county": "Madison",
    "pop": 18046
  },
  {"state" : "IN",
    "zip": "46404",
    "city": "Gary",
    "county": "Lake",
    "pop": 17894
  },
  {"state" : "IN",
    "zip": "47501",
    "city": "Washington",
    "county": "Daviess",
    "pop": 17882
  },
  {"state" : "IN",
    "zip": "47172",
    "city": "Sellersburg",
    "county": "Clark",
    "pop": 17813
  },
  {"state" : "IN",
    "zip": "47720",
    "city": "Evansville",
    "county": "Vanderburgh",
    "pop": 17763
  },
  {"state" : "IN",
    "zip": "46356",
    "city": "Lowell",
    "county": "Lake",
    "pop": 17720
  },
  {"state" : "IN",
    "zip": "46807",
    "city": "Fort Wayne",
    "county": "Allen",
    "pop": 17538
  },
  {"state" : "IN",
    "zip": "46319",
    "city": "Griffith",
    "county": "Lake",
    "pop": 17513
  },
  {"state" : "IN",
    "zip": "47725",
    "city": "Evansville",
    "county": "Vanderburgh",
    "pop": 17326
  },
  {"state" : "IN",
    "zip": "47904",
    "city": "Lafayette",
    "county": "Tippecanoe",
    "pop": 17285
  },
  {"state" : "IN",
    "zip": "46774",
    "city": "New Haven",
    "county": "Allen",
    "pop": 17221
  },
  {"state" : "IN",
    "zip": "46064",
    "city": "Pendleton",
    "county": "Madison",
    "pop": 17168
  },
  {"state" : "IN",
    "zip": "46013",
    "city": "Anderson",
    "county": "Madison",
    "pop": 17136
  },
  {"state" : "IN",
    "zip": "46011",
    "city": "Anderson",
    "county": "Madison",
    "pop": 17069
  },
  {"state" : "IN",
    "zip": "47111",
    "city": "Charlestown",
    "county": "Clark",
    "pop": 16971
  },
  {"state" : "IN",
    "zip": "47112",
    "city": "Corydon",
    "county": "Harrison",
    "pop": 16593
  },
  {"state" : "IN",
    "zip": "46228",
    "city": "Indianapolis",
    "county": "Marion",
    "pop": 16430
  },
  {"state" : "IN",
    "zip": "46122",
    "city": "Danville",
    "county": "Hendricks",
    "pop": 16300
  },
  {"state" : "IN",
    "zip": "46992",
    "city": "Wabash",
    "county": "Wabash",
    "pop": 16260
  },
  {"state" : "IN",
    "zip": "46637",
    "city": "South Bend",
    "county": "St Joseph",
    "pop": 16090
  },
  {"state" : "IN",
    "zip": "46373",
    "city": "Saint John",
    "county": "Lake",
    "pop": 16083
  },
  {"state" : "IN",
    "zip": "46408",
    "city": "Gary",
    "county": "Lake",
    "pop": 15526
  },
  {"state" : "IN",
    "zip": "46113",
    "city": "Camby",
    "county": "Marion",
    "pop": 15505
  },
  {"state" : "IN",
    "zip": "46755",
    "city": "Kendallville",
    "county": "Noble",
    "pop": 15097
  },
  {"state" : "IN",
    "zip": "46714",
    "city": "Bluffton",
    "county": "Wells",
    "pop": 14931
  },
  {"state" : "IN",
    "zip": "47170",
    "city": "Scottsburg",
    "county": "Scott",
    "pop": 14919
  },
  {"state" : "IN",
    "zip": "47167",
    "city": "Salem",
    "county": "Washington",
    "pop": 14879
  },
  {"state" : "IN",
    "zip": "46303",
    "city": "Cedar Lake",
    "county": "Lake",
    "pop": 14765
  },
  {"state" : "IN",
    "zip": "47960",
    "city": "Monticello",
    "county": "White",
    "pop": 14721
  },
  {"state" : "IN",
    "zip": "46975",
    "city": "Rochester",
    "county": "Fulton",
    "pop": 14325
  },
  {"state" : "IN",
    "zip": "46184",
    "city": "Whiteland",
    "county": "Johnson",
    "pop": 14042
  },
  {"state" : "IN",
    "zip": "47601",
    "city": "Boonville",
    "county": "Warrick",
    "pop": 13854
  },
  {"state" : "IN",
    "zip": "46310",
    "city": "Demotte",
    "county": "Jasper",
    "pop": 13832
  },
  {"state" : "IN",
    "zip": "46615",
    "city": "South Bend",
    "county": "St Joseph",
    "pop": 13719
  },
  {"state" : "IN",
    "zip": "46561",
    "city": "Osceola",
    "county": "St Joseph",
    "pop": 13615
  },
  {"state" : "IN",
    "zip": "46320",
    "city": "Hammond",
    "county": "Lake",
    "pop": 13561
  },
  {"state" : "IN",
    "zip": "46582",
    "city": "Warsaw",
    "county": "Kosciusko",
    "pop": 13459
  },
  {"state" : "IN",
    "zip": "46403",
    "city": "Gary",
    "county": "Lake",
    "pop": 13435
  },
  {"state" : "IN",
    "zip": "47620",
    "city": "Mount Vernon",
    "county": "Posey",
    "pop": 13129
  },
  {"state" : "IN",
    "zip": "46163",
    "city": "New Palestine",
    "county": "Hancock",
    "pop": 13088
  },
  {"state" : "IN",
    "zip": "46107",
    "city": "Beech Grove",
    "county": "Marion",
    "pop": 13081
  },
  {"state" : "IN",
    "zip": "46814",
    "city": "Fort Wayne",
    "county": "Allen",
    "pop": 12649
  },
  {"state" : "IN",
    "zip": "46055",
    "city": "Mc Cordsville",
    "county": "Hancock",
    "pop": 12638
  },
  {"state" : "IN",
    "zip": "46550",
    "city": "Nappanee",
    "county": "Elkhart",
    "pop": 12624
  },
  {"state" : "IN",
    "zip": "47805",
    "city": "Terre Haute",
    "county": "Vigo",
    "pop": 12624
  },
  {"state" : "IN",
    "zip": "46040",
    "city": "Fortville",
    "county": "Hancock",
    "pop": 12474
  },
  {"state" : "IN",
    "zip": "46761",
    "city": "Lagrange",
    "county": "Lagrange",
    "pop": 12325
  },
  {"state" : "IN",
    "zip": "46394",
    "city": "Whiting",
    "county": "Lake",
    "pop": 12319
  },
  {"state" : "IN",
    "zip": "47371",
    "city": "Portland",
    "county": "Jay",
    "pop": 12200
  },
  {"state" : "IN",
    "zip": "47670",
    "city": "Princeton",
    "county": "Gibson",
    "pop": 12048
  },
  {"state" : "IN",
    "zip": "47807",
    "city": "Terre Haute",
    "county": "Vigo",
    "pop": 11886
  },
  {"state" : "IN",
    "zip": "46540",
    "city": "Middlebury",
    "county": "Elkhart",
    "pop": 11881
  },
  {"state" : "IN",
    "zip": "47006",
    "city": "Batesville",
    "county": "Ripley",
    "pop": 11880
  },
  {"state" : "IN",
    "zip": "47804",
    "city": "Terre Haute",
    "county": "Vigo",
    "pop": 11781
  },
  {"state" : "IN",
    "zip": "47119",
    "city": "Floyds Knobs",
    "county": "Floyd",
    "pop": 11700
  },
  {"state" : "IN",
    "zip": "46534",
    "city": "Knox",
    "county": "Starke",
    "pop": 11686
  },
  {"state" : "IN",
    "zip": "46036",
    "city": "Elwood",
    "county": "Madison",
    "pop": 11678
  },
  {"state" : "IN",
    "zip": "47978",
    "city": "Rensselaer",
    "county": "Jasper",
    "pop": 11515
  },
  {"state" : "IN",
    "zip": "46327",
    "city": "Hammond",
    "county": "Lake",
    "pop": 11466
  },
  {"state" : "IN",
    "zip": "46613",
    "city": "South Bend",
    "county": "St Joseph",
    "pop": 11327
  },
  {"state" : "IN",
    "zip": "47586",
    "city": "Tell City",
    "county": "Perry",
    "pop": 11022
  },
  {"state" : "IN",
    "zip": "46259",
    "city": "Indianapolis",
    "county": "Marion",
    "pop": 10999
  },
  {"state" : "IN",
    "zip": "47122",
    "city": "Georgetown",
    "county": "Floyd",
    "pop": 10943
  },
  {"state" : "IN",
    "zip": "47460",
    "city": "Spencer",
    "county": "Owen",
    "pop": 10917
  },
  {"state" : "IN",
    "zip": "46407",
    "city": "Gary",
    "county": "Lake",
    "pop": 10905
  },
  {"state" : "IN",
    "zip": "46405",
    "city": "Lake Station",
    "county": "Lake",
    "pop": 10855
  },
  {"state" : "IN",
    "zip": "46802",
    "city": "Fort Wayne",
    "county": "Allen",
    "pop": 10584
  },
  {"state" : "IN",
    "zip": "47446",
    "city": "Mitchell",
    "county": "Lawrence",
    "pop": 10393
  },
  {"state" : "IN",
    "zip": "46341",
    "city": "Hebron",
    "county": "Porter",
    "pop": 10357
  },
  {"state" : "IN",
    "zip": "46231",
    "city": "Indianapolis",
    "county": "Marion",
    "pop": 10277
  },
  {"state" : "IN",
    "zip": "47713",
    "city": "Evansville",
    "county": "Vanderburgh",
    "pop": 10108
  },
  {"state" : "IN",
    "zip": "47542",
    "city": "Huntingburg",
    "county": "Dubois",
    "pop": 10061
  },
  {"state" : "IN",
    "zip": "47001",
    "city": "Aurora",
    "county": "Dearborn",
    "pop": 10009
  },
  {"state" : "IN",
    "zip": "46001",
    "city": "Alexandria",
    "county": "Madison",
    "pop": 9993
  },
  {"state" : "IN",
    "zip": "46173",
    "city": "Rushville",
    "county": "Rush",
    "pop": 9905
  },
  {"state" : "IN",
    "zip": "46506",
    "city": "Bremen",
    "county": "Marshall",
    "pop": 9700
  },
  {"state" : "IN",
    "zip": "46617",
    "city": "South Bend",
    "county": "St Joseph",
    "pop": 9689
  },
  {"state" : "IN",
    "zip": "46819",
    "city": "Fort Wayne",
    "county": "Allen",
    "pop": 9657
  },
  {"state" : "IN",
    "zip": "47842",
    "city": "Clinton",
    "county": "Vermillion",
    "pop": 9597
  },
  {"state" : "IN",
    "zip": "46391",
    "city": "Westville",
    "county": "La Porte",
    "pop": 9528
  },
  {"state" : "IN",
    "zip": "46574",
    "city": "Walkerton",
    "county": "St Joseph",
    "pop": 9436
  },
  {"state" : "IN",
    "zip": "46507",
    "city": "Bristol",
    "county": "Elkhart",
    "pop": 9434
  },
  {"state" : "IN",
    "zip": "46803",
    "city": "Fort Wayne",
    "county": "Allen",
    "pop": 9425
  },
  {"state" : "IN",
    "zip": "47012",
    "city": "Brookville",
    "county": "Franklin",
    "pop": 9396
  },
  {"state" : "IN",
    "zip": "47429",
    "city": "Ellettsville",
    "county": "Monroe",
    "pop": 9269
  },
  {"state" : "IN",
    "zip": "46809",
    "city": "Fort Wayne",
    "county": "Allen",
    "pop": 9212
  },
  {"state" : "IN",
    "zip": "46567",
    "city": "Syracuse",
    "county": "Kosciusko",
    "pop": 9162
  },
  {"state" : "IN",
    "zip": "47348",
    "city": "Hartford City",
    "county": "Blackford",
    "pop": 9159
  },
  {"state" : "IN",
    "zip": "47441",
    "city": "Linton",
    "county": "Greene",
    "pop": 9153
  },
  {"state" : "IN",
    "zip": "46406",
    "city": "Gary",
    "county": "Lake",
    "pop": 9042
  },
  {"state" : "IN",
    "zip": "47424",
    "city": "Bloomfield",
    "county": "Greene",
    "pop": 8965
  },
  {"state" : "IN",
    "zip": "46124",
    "city": "Edinburgh",
    "county": "Johnson",
    "pop": 8949
  },
  {"state" : "IN",
    "zip": "47885",
    "city": "West Terre Haute",
    "county": "Vigo",
    "pop": 8920
  },
  {"state" : "IN",
    "zip": "46278",
    "city": "Indianapolis",
    "county": "Marion",
    "pop": 8859
  },
  {"state" : "IN",
    "zip": "46962",
    "city": "North Manchester",
    "county": "Wabash",
    "pop": 8844
  },
  {"state" : "IN",
    "zip": "46711",
    "city": "Berne",
    "county": "Adams",
    "pop": 8770
  },
  {"state" : "IN",
    "zip": "47872",
    "city": "Rockville",
    "county": "Parke",
    "pop": 8747
  },
  {"state" : "IN",
    "zip": "46565",
    "city": "Shipshewana",
    "county": "Lagrange",
    "pop": 8642
  },
  {"state" : "IN",
    "zip": "47553",
    "city": "Loogootee",
    "county": "Martin",
    "pop": 8614
  },
  {"state" : "IN",
    "zip": "46072",
    "city": "Tipton",
    "county": "Tipton",
    "pop": 8592
  },
  {"state" : "IN",
    "zip": "46738",
    "city": "Garrett",
    "county": "De Kalb",
    "pop": 8549
  },
  {"state" : "IN",
    "zip": "46204",
    "city": "Indianapolis",
    "county": "Marion",
    "pop": 8356
  },
  {"state" : "IN",
    "zip": "47394",
    "city": "Winchester",
    "county": "Randolph",
    "pop": 8334
  },
  {"state" : "IN",
    "zip": "46767",
    "city": "Ligonier",
    "county": "Noble",
    "pop": 8102
  },
  {"state" : "IN",
    "zip": "46701",
    "city": "Albion",
    "county": "Noble",
    "pop": 8102
  },
  {"state" : "IN",
    "zip": "46923",
    "city": "Delphi",
    "county": "Carroll",
    "pop": 8046
  },
  {"state" : "IN",
    "zip": "46723",
    "city": "Churubusco",
    "county": "Whitley",
    "pop": 7884
  },
  {"state" : "IN",
    "zip": "46392",
    "city": "Wheatfield",
    "county": "Jasper",
    "pop": 7734
  },
  {"state" : "IN",
    "zip": "47882",
    "city": "Sullivan",
    "county": "Sullivan",
    "pop": 7731
  },
  {"state" : "IN",
    "zip": "46737",
    "city": "Fremont",
    "county": "Steuben",
    "pop": 7329
  },
  {"state" : "IN",
    "zip": "46556",
    "city": "Notre Dame",
    "county": "St Joseph",
    "pop": 7301
  },
  {"state" : "IN",
    "zip": "47448",
    "city": "Nashville",
    "county": "Brown",
    "pop": 7261
  },
  {"state" : "IN",
    "zip": "46069",
    "city": "Sheridan",
    "county": "Hamilton",
    "pop": 7220
  },
  {"state" : "IN",
    "zip": "46409",
    "city": "Gary",
    "county": "Lake",
    "pop": 7205
  },
  {"state" : "IN",
    "zip": "46167",
    "city": "Pittsboro",
    "county": "Hendricks",
    "pop": 7066
  },
  {"state" : "IN",
    "zip": "47454",
    "city": "Paoli",
    "county": "Orange",
    "pop": 7046
  },
  {"state" : "IN",
    "zip": "47102",
    "city": "Austin",
    "county": "Scott",
    "pop": 6953
  },
  {"state" : "IN",
    "zip": "46552",
    "city": "New Carlisle",
    "county": "St Joseph",
    "pop": 6907
  },
  {"state" : "IN",
    "zip": "47396",
    "city": "Yorktown",
    "county": "Delaware",
    "pop": 6903
  },
  {"state" : "IN",
    "zip": "46106",
    "city": "Bargersville",
    "county": "Johnson",
    "pop": 6855
  },
  {"state" : "IN",
    "zip": "46280",
    "city": "Indianapolis",
    "county": "Hamilton",
    "pop": 6824
  },
  {"state" : "IN",
    "zip": "46795",
    "city": "Wolcottville",
    "county": "Lagrange",
    "pop": 6651
  },
  {"state" : "IN",
    "zip": "46783",
    "city": "Roanoke",
    "county": "Huntington",
    "pop": 6651
  },
  {"state" : "IN",
    "zip": "46034",
    "city": "Cicero",
    "county": "Hamilton",
    "pop": 6649
  },
  {"state" : "IN",
    "zip": "47041",
    "city": "Sunman",
    "county": "Ripley",
    "pop": 6626
  },
  {"state" : "IN",
    "zip": "46075",
    "city": "Whitestown",
    "county": "Boone",
    "pop": 6614
  },
  {"state" : "IN",
    "zip": "46777",
    "city": "Ossian",
    "county": "Wells",
    "pop": 6493
  },
  {"state" : "IN",
    "zip": "46635",
    "city": "South Bend",
    "county": "St Joseph",
    "pop": 6363
  },
  {"state" : "IN",
    "zip": "46160",
    "city": "Morgantown",
    "county": "Brown",
    "pop": 6321
  },
  {"state" : "IN",
    "zip": "46402",
    "city": "Gary",
    "county": "Lake",
    "pop": 6295
  },
  {"state" : "IN",
    "zip": "46996",
    "city": "Winamac",
    "county": "Pulaski",
    "pop": 6159
  },
  {"state" : "IN",
    "zip": "46933",
    "city": "Gas City",
    "county": "Grant",
    "pop": 6126
  },
  {"state" : "IN",
    "zip": "47567",
    "city": "Petersburg",
    "county": "Pike",
    "pop": 6116
  },
  {"state" : "IN",
    "zip": "47165",
    "city": "Pekin",
    "county": "Washington",
    "pop": 6034
  },
  {"state" : "IN",
    "zip": "47060",
    "city": "West Harrison",
    "county": "Dearborn",
    "pop": 5942
  },
  {"state" : "IN",
    "zip": "47243",
    "city": "Hanover",
    "county": "Jefferson",
    "pop": 5907
  },
  {"state" : "IN",
    "zip": "46936",
    "city": "Greentown",
    "county": "Howard",
    "pop": 5857
  },
  {"state" : "IN",
    "zip": "46017",
    "city": "Anderson",
    "county": "Madison",
    "pop": 5814
  },
  {"state" : "IN",
    "zip": "46601",
    "city": "South Bend",
    "county": "St Joseph",
    "pop": 5714
  },
  {"state" : "IN",
    "zip": "46571",
    "city": "Topeka",
    "county": "Lagrange",
    "pop": 5682
  },
  {"state" : "IN",
    "zip": "47918",
    "city": "Attica",
    "county": "Fountain",
    "pop": 5679
  },
  {"state" : "IN",
    "zip": "47220",
    "city": "Brownstown",
    "county": "Jackson",
    "pop": 5671
  },
  {"state" : "IN",
    "zip": "46366",
    "city": "North Judson",
    "county": "Starke",
    "pop": 5610
  },
  {"state" : "IN",
    "zip": "46225",
    "city": "Indianapolis",
    "county": "Marion",
    "pop": 5577
  },
  {"state" : "IN",
    "zip": "46765",
    "city": "Leo",
    "county": "Allen",
    "pop": 5568
  },
  {"state" : "IN",
    "zip": "46148",
    "city": "Knightstown",
    "county": "Henry",
    "pop": 5555
  },
  {"state" : "IN",
    "zip": "46121",
    "city": "Coatesville",
    "county": "Hendricks",
    "pop": 5545
  },
  {"state" : "IN",
    "zip": "47353",
    "city": "Liberty",
    "county": "Union",
    "pop": 5508
  },
  {"state" : "IN",
    "zip": "47031",
    "city": "Milan",
    "county": "Ripley",
    "pop": 5477
  },
  {"state" : "IN",
    "zip": "46616",
    "city": "South Bend",
    "county": "St Joseph",
    "pop": 5457
  },
  {"state" : "IN",
    "zip": "47610",
    "city": "Chandler",
    "county": "Warrick",
    "pop": 5444
  },
  {"state" : "IN",
    "zip": "47635",
    "city": "Rockport",
    "county": "Spencer",
    "pop": 5432
  },
  {"state" : "IN",
    "zip": "47452",
    "city": "Orleans",
    "county": "Orange",
    "pop": 5360
  },
  {"state" : "IN",
    "zip": "46120",
    "city": "Cloverdale",
    "county": "Putnam",
    "pop": 5332
  },
  {"state" : "IN",
    "zip": "47932",
    "city": "Covington",
    "county": "Fountain",
    "pop": 5317
  },
  {"state" : "IN",
    "zip": "46181",
    "city": "Trafalgar",
    "county": "Johnson",
    "pop": 5286
  },
  {"state" : "IN",
    "zip": "47356",
    "city": "Middletown",
    "county": "Henry",
    "pop": 5286
  },
  {"state" : "IN",
    "zip": "47043",
    "city": "Vevay",
    "county": "Switzerland",
    "pop": 5212
  },
  {"state" : "IN",
    "zip": "47330",
    "city": "Centerville",
    "county": "Wayne",
    "pop": 5196
  },
  {"state" : "IN",
    "zip": "47124",
    "city": "Greenville",
    "county": "Floyd",
    "pop": 5146
  },
  {"state" : "IN",
    "zip": "47040",
    "city": "Rising Sun",
    "county": "Ohio",
    "pop": 5103
  },
  {"state" : "IN",
    "zip": "47306",
    "city": "Muncie",
    "county": "Delaware",
    "pop": 5096
  },
  {"state" : "IN",
    "zip": "46721",
    "city": "Butler",
    "county": "De Kalb",
    "pop": 5084
  },
  {"state" : "IN",
    "zip": "46118",
    "city": "Clayton",
    "county": "Hendricks",
    "pop": 5068
  },
  {"state" : "IN",
    "zip": "46748",
    "city": "Huntertown",
    "county": "Allen",
    "pop": 5021
  },
  {"state" : "IN",
    "zip": "46562",
    "city": "Pierceton",
    "county": "Kosciusko",
    "pop": 5010
  },
  {"state" : "IN",
    "zip": "47106",
    "city": "Borden",
    "county": "Clark",
    "pop": 5005
  },
  {"state" : "IN",
    "zip": "47390",
    "city": "Union City",
    "county": "Randolph",
    "pop": 4960
  },
  {"state" : "IN",
    "zip": "46126",
    "city": "Fairland",
    "county": "Shelby",
    "pop": 4956
  },
  {"state" : "IN",
    "zip": "46989",
    "city": "Upland",
    "county": "Grant",
    "pop": 4947
  },
  {"state" : "IN",
    "zip": "46979",
    "city": "Russiaville",
    "county": "Howard",
    "pop": 4940
  },
  {"state" : "IN",
    "zip": "46590",
    "city": "Winona Lake",
    "county": "Kosciusko",
    "pop": 4925
  },
  {"state" : "IN",
    "zip": "46554",
    "city": "North Liberty",
    "county": "St Joseph",
    "pop": 4878
  },
  {"state" : "IN",
    "zip": "46793",
    "city": "Waterloo",
    "county": "De Kalb",
    "pop": 4874
  },
  {"state" : "IN",
    "zip": "47660",
    "city": "Oakland City",
    "county": "Gibson",
    "pop": 4868
  },
  {"state" : "IN",
    "zip": "46347",
    "city": "Kouts",
    "county": "Porter",
    "pop": 4833
  },
  {"state" : "IN",
    "zip": "47462",
    "city": "Springville",
    "county": "Lawrence",
    "pop": 4812
  },
  {"state" : "IN",
    "zip": "47562",
    "city": "Odon",
    "county": "Daviess",
    "pop": 4755
  },
  {"state" : "IN",
    "zip": "47126",
    "city": "Henryville",
    "county": "Clark",
    "pop": 4698
  },
  {"state" : "IN",
    "zip": "46746",
    "city": "Howe",
    "county": "Lagrange",
    "pop": 4640
  },
  {"state" : "IN",
    "zip": "47558",
    "city": "Montgomery",
    "county": "Daviess",
    "pop": 4632
  },
  {"state" : "IN",
    "zip": "47246",
    "city": "Hope",
    "county": "Bartholomew",
    "pop": 4600
  },
  {"state" : "IN",
    "zip": "47037",
    "city": "Osgood",
    "county": "Ripley",
    "pop": 4553
  },
  {"state" : "IN",
    "zip": "46741",
    "city": "Grabill",
    "county": "Allen",
    "pop": 4553
  },
  {"state" : "IN",
    "zip": "47117",
    "city": "Elizabeth",
    "county": "Harrison",
    "pop": 4531
  },
  {"state" : "IN",
    "zip": "47327",
    "city": "Cambridge City",
    "county": "Wayne",
    "pop": 4512
  },
  {"state" : "IN",
    "zip": "47136",
    "city": "Lanesville",
    "county": "Harrison",
    "pop": 4482
  },
  {"state" : "IN",
    "zip": "47018",
    "city": "Dillsboro",
    "county": "Dearborn",
    "pop": 4477
  },
  {"state" : "IN",
    "zip": "47438",
    "city": "Jasonville",
    "county": "Greene",
    "pop": 4475
  },
  {"state" : "IN",
    "zip": "47432",
    "city": "French Lick",
    "county": "Orange",
    "pop": 4386
  },
  {"state" : "IN",
    "zip": "47138",
    "city": "Lexington",
    "county": "Scott",
    "pop": 4378
  },
  {"state" : "IN",
    "zip": "47532",
    "city": "Ferdinand",
    "county": "Dubois",
    "pop": 4358
  },
  {"state" : "IN",
    "zip": "46511",
    "city": "Culver",
    "county": "Marshall",
    "pop": 4308
  },
  {"state" : "IN",
    "zip": "46710",
    "city": "Avilla",
    "county": "Noble",
    "pop": 4291
  },
  {"state" : "IN",
    "zip": "46928",
    "city": "Fairmount",
    "county": "Grant",
    "pop": 4265
  },
  {"state" : "IN",
    "zip": "47639",
    "city": "Haubstadt",
    "county": "Gibson",
    "pop": 4243
  },
  {"state" : "IN",
    "zip": "47648",
    "city": "Fort Branch",
    "county": "Gibson",
    "pop": 4219
  },
  {"state" : "IN",
    "zip": "46538",
    "city": "Leesburg",
    "county": "Kosciusko",
    "pop": 4169
  },
  {"state" : "IN",
    "zip": "46164",
    "city": "Nineveh",
    "county": "Johnson",
    "pop": 4166
  },
  {"state" : "IN",
    "zip": "46542",
    "city": "Milford",
    "county": "Kosciusko",
    "pop": 4142
  },
  {"state" : "IN",
    "zip": "47164",
    "city": "Palmyra",
    "county": "Harrison",
    "pop": 4115
  },
  {"state" : "IN",
    "zip": "46157",
    "city": "Monrovia",
    "county": "Morgan",
    "pop": 4103
  },
  {"state" : "IN",
    "zip": "47512",
    "city": "Bicknell",
    "county": "Knox",
    "pop": 4095
  },
  {"state" : "IN",
    "zip": "47042",
    "city": "Versailles",
    "county": "Ripley",
    "pop": 4089
  },
  {"state" : "IN",
    "zip": "47987",
    "city": "Veedersburg",
    "county": "Fountain",
    "pop": 4074
  },
  {"state" : "IN",
    "zip": "47433",
    "city": "Gosport",
    "county": "Owen",
    "pop": 4039
  },
  {"state" : "IN",
    "zip": "47406",
    "city": "Bloomington",
    "county": "Monroe",
    "pop": 3945
  },
  {"state" : "IN",
    "zip": "46510",
    "city": "Claypool",
    "county": "Kosciusko",
    "pop": 3924
  },
  {"state" : "IN",
    "zip": "46797",
    "city": "Woodburn",
    "county": "Allen",
    "pop": 3915
  },
  {"state" : "IN",
    "zip": "47346",
    "city": "Hagerstown",
    "county": "Wayne",
    "pop": 3911
  },
  {"state" : "IN",
    "zip": "46740",
    "city": "Geneva",
    "county": "Adams",
    "pop": 3874
  },
  {"state" : "IN",
    "zip": "46787",
    "city": "South Whitley",
    "county": "Whitley",
    "pop": 3865
  },
  {"state" : "IN",
    "zip": "46573",
    "city": "Wakarusa",
    "county": "Elkhart",
    "pop": 3812
  },
  {"state" : "IN",
    "zip": "47838",
    "city": "Carlisle",
    "county": "Sullivan",
    "pop": 3772
  },
  {"state" : "IN",
    "zip": "46792",
    "city": "Warren",
    "county": "Huntington",
    "pop": 3756
  },
  {"state" : "IN",
    "zip": "47665",
    "city": "Owensville",
    "county": "Gibson",
    "pop": 3746
  },
  {"state" : "IN",
    "zip": "46504",
    "city": "Bourbon",
    "county": "Marshall",
    "pop": 3735
  },
  {"state" : "IN",
    "zip": "46788",
    "city": "Spencerville",
    "county": "De Kalb",
    "pop": 3723
  },
  {"state" : "IN",
    "zip": "47581",
    "city": "Shoals",
    "county": "Martin",
    "pop": 3721
  },
  {"state" : "IN",
    "zip": "47901",
    "city": "Lafayette",
    "county": "Tippecanoe",
    "pop": 3715
  },
  {"state" : "IN",
    "zip": "47024",
    "city": "Laurel",
    "county": "Franklin",
    "pop": 3708
  },
  {"state" : "IN",
    "zip": "47405",
    "city": "Bloomington",
    "county": "Monroe",
    "pop": 3697
  },
  {"state" : "IN",
    "zip": "47993",
    "city": "Williamsport",
    "county": "Warren",
    "pop": 3661
  },
  {"state" : "IN",
    "zip": "47320",
    "city": "Albany",
    "county": "Delaware",
    "pop": 3648
  },
  {"state" : "IN",
    "zip": "46501",
    "city": "Argos",
    "county": "Marshall",
    "pop": 3613
  },
  {"state" : "IN",
    "zip": "47459",
    "city": "Solsberry",
    "county": "Greene",
    "pop": 3597
  },
  {"state" : "IN",
    "zip": "47879",
    "city": "Shelburn",
    "county": "Sullivan",
    "pop": 3592
  },
  {"state" : "IN",
    "zip": "46543",
    "city": "Millersburg",
    "county": "Elkhart",
    "pop": 3553
  },
  {"state" : "IN",
    "zip": "47638",
    "city": "Wadesville",
    "county": "Posey",
    "pop": 3514
  },
  {"state" : "IN",
    "zip": "47305",
    "city": "Muncie",
    "county": "Delaware",
    "pop": 3504
  },
  {"state" : "IN",
    "zip": "47118",
    "city": "English",
    "county": "Crawford",
    "pop": 3474
  },
  {"state" : "IN",
    "zip": "46065",
    "city": "Rossville",
    "county": "Clinton",
    "pop": 3444
  },
  {"state" : "IN",
    "zip": "47944",
    "city": "Fowler",
    "county": "Benton",
    "pop": 3402
  },
  {"state" : "IN",
    "zip": "46773",
    "city": "Monroeville",
    "county": "Allen",
    "pop": 3392
  },
  {"state" : "IN",
    "zip": "46910",
    "city": "Akron",
    "county": "Fulton",
    "pop": 3376
  },
  {"state" : "IN",
    "zip": "47523",
    "city": "Dale",
    "county": "Spencer",
    "pop": 3346
  },
  {"state" : "IN",
    "zip": "46390",
    "city": "Wanatah",
    "county": "La Porte",
    "pop": 3327
  },
  {"state" : "IN",
    "zip": "47232",
    "city": "Elizabethtown",
    "county": "Bartholomew",
    "pop": 3327
  },
  {"state" : "IN",
    "zip": "47161",
    "city": "New Salisbury",
    "county": "Harrison",
    "pop": 3305
  },
  {"state" : "IN",
    "zip": "46742",
    "city": "Hamilton",
    "county": "Steuben",
    "pop": 3290
  },
  {"state" : "IN",
    "zip": "47229",
    "city": "Crothersville",
    "county": "Jackson",
    "pop": 3261
  },
  {"state" : "IN",
    "zip": "46349",
    "city": "Lake Village",
    "county": "Newton",
    "pop": 3251
  },
  {"state" : "IN",
    "zip": "46371",
    "city": "Rolling Prairie",
    "county": "La Porte",
    "pop": 3246
  },
  {"state" : "IN",
    "zip": "46732",
    "city": "Cromwell",
    "county": "Noble",
    "pop": 3244
  },
  {"state" : "IN",
    "zip": "47336",
    "city": "Dunkirk",
    "county": "Jay",
    "pop": 3243
  },
  {"state" : "IN",
    "zip": "46553",
    "city": "New Paris",
    "county": "Elkhart",
    "pop": 3240
  },
  {"state" : "IN",
    "zip": "47613",
    "city": "Elberfeld",
    "county": "Warrick",
    "pop": 3224
  },
  {"state" : "IN",
    "zip": "47923",
    "city": "Brookston",
    "county": "White",
    "pop": 3220
  },
  {"state" : "IN",
    "zip": "46536",
    "city": "Lakeville",
    "county": "St Joseph",
    "pop": 3209
  },
  {"state" : "IN",
    "zip": "46147",
    "city": "Jamestown",
    "county": "Boone",
    "pop": 3209
  },
  {"state" : "IN",
    "zip": "47874",
    "city": "Rosedale",
    "county": "Parke",
    "pop": 3207
  },
  {"state" : "IN",
    "zip": "47283",
    "city": "Westport",
    "county": "Decatur",
    "pop": 3193
  },
  {"state" : "IN",
    "zip": "47334",
    "city": "Daleville",
    "county": "Delaware",
    "pop": 3189
  },
  {"state" : "IN",
    "zip": "46071",
    "city": "Thorntown",
    "county": "Boone",
    "pop": 3148
  },
  {"state" : "IN",
    "zip": "46044",
    "city": "Frankton",
    "county": "Madison",
    "pop": 3147
  },
  {"state" : "IN",
    "zip": "47383",
    "city": "Selma",
    "county": "Delaware",
    "pop": 3133
  },
  {"state" : "IN",
    "zip": "47032",
    "city": "Moores Hill",
    "county": "Dearborn",
    "pop": 3116
  },
  {"state" : "IN",
    "zip": "46929",
    "city": "Flora",
    "county": "Carroll",
    "pop": 3088
  },
  {"state" : "IN",
    "zip": "46772",
    "city": "Monroe",
    "county": "Adams",
    "pop": 3087
  },
  {"state" : "IN",
    "zip": "47868",
    "city": "Poland",
    "county": "Clay",
    "pop": 3072
  },
  {"state" : "IN",
    "zip": "47143",
    "city": "Memphis",
    "county": "Clark",
    "pop": 3063
  },
  {"state" : "IN",
    "zip": "47598",
    "city": "Winslow",
    "county": "Pike",
    "pop": 3058
  },
  {"state" : "IN",
    "zip": "46770",
    "city": "Markle",
    "county": "Huntington",
    "pop": 3057
  },
  {"state" : "IN",
    "zip": "46932",
    "city": "Galveston",
    "county": "Cass",
    "pop": 3057
  },
  {"state" : "IN",
    "zip": "47115",
    "city": "Depauw",
    "county": "Harrison",
    "pop": 3025
  },
  {"state" : "IN",
    "zip": "47359",
    "city": "Montpelier",
    "county": "Blackford",
    "pop": 3013
  },
  {"state" : "IN",
    "zip": "47340",
    "city": "Farmland",
    "county": "Randolph",
    "pop": 2998
  },
  {"state" : "IN",
    "zip": "47022",
    "city": "Guilford",
    "county": "Dearborn",
    "pop": 2980
  },
  {"state" : "IN",
    "zip": "46030",
    "city": "Arcadia",
    "county": "Hamilton",
    "pop": 2978
  },
  {"state" : "IN",
    "zip": "47952",
    "city": "Kingman",
    "county": "Fountain",
    "pop": 2941
  },
  {"state" : "IN",
    "zip": "46938",
    "city": "Jonesboro",
    "county": "Grant",
    "pop": 2928
  },
  {"state" : "IN",
    "zip": "47959",
    "city": "Monon",
    "county": "White",
    "pop": 2906
  },
  {"state" : "IN",
    "zip": "46068",
    "city": "Sharpsville",
    "county": "Tipton",
    "pop": 2872
  },
  {"state" : "IN",
    "zip": "47368",
    "city": "Parker City",
    "county": "Randolph",
    "pop": 2831
  },
  {"state" : "IN",
    "zip": "46051",
    "city": "Lapel",
    "county": "Madison",
    "pop": 2817
  },
  {"state" : "IN",
    "zip": "46994",
    "city": "Walton",
    "county": "Cass",
    "pop": 2815
  },
  {"state" : "IN",
    "zip": "46539",
    "city": "Mentone",
    "county": "Kosciusko",
    "pop": 2802
  },
  {"state" : "IN",
    "zip": "47338",
    "city": "Eaton",
    "county": "Delaware",
    "pop": 2789
  },
  {"state" : "IN",
    "zip": "47520",
    "city": "Cannelton",
    "county": "Perry",
    "pop": 2786
  },
  {"state" : "IN",
    "zip": "47355",
    "city": "Lynn",
    "county": "Randolph",
    "pop": 2752
  },
  {"state" : "IN",
    "zip": "47471",
    "city": "Worthington",
    "county": "Greene",
    "pop": 2746
  },
  {"state" : "IN",
    "zip": "46130",
    "city": "Fountaintown",
    "county": "Shelby",
    "pop": 2669
  },
  {"state" : "IN",
    "zip": "46982",
    "city": "Silver Lake",
    "county": "Kosciusko",
    "pop": 2660
  },
  {"state" : "IN",
    "zip": "46940",
    "city": "La Fontaine",
    "county": "Wabash",
    "pop": 2658
  },
  {"state" : "IN",
    "zip": "47579",
    "city": "Santa Claus",
    "county": "Spencer",
    "pop": 2636
  },
  {"state" : "IN",
    "zip": "46161",
    "city": "Morristown",
    "county": "Shelby",
    "pop": 2569
  },
  {"state" : "IN",
    "zip": "46172",
    "city": "Roachdale",
    "county": "Putnam",
    "pop": 2562
  },
  {"state" : "IN",
    "zip": "47140",
    "city": "Marengo",
    "county": "Crawford",
    "pop": 2559
  },
  {"state" : "IN",
    "zip": "47342",
    "city": "Gaston",
    "county": "Delaware",
    "pop": 2558
  },
  {"state" : "IN",
    "zip": "46031",
    "city": "Atlanta",
    "county": "Hamilton",
    "pop": 2546
  },
  {"state" : "IN",
    "zip": "46058",
    "city": "Mulberry",
    "county": "Clinton",
    "pop": 2516
  },
  {"state" : "IN",
    "zip": "47809",
    "city": "Terre Haute",
    "county": "Vigo",
    "pop": 2516
  },
  {"state" : "IN",
    "zip": "47954",
    "city": "Ladoga",
    "county": "Montgomery",
    "pop": 2433
  },
  {"state" : "IN",
    "zip": "46919",
    "city": "Converse",
    "county": "Miami",
    "pop": 2407
  },
  {"state" : "IN",
    "zip": "46555",
    "city": "North Webster",
    "county": "Kosciusko",
    "pop": 2406
  },
  {"state" : "IN",
    "zip": "47373",
    "city": "Redkey",
    "county": "Jay",
    "pop": 2404
  },
  {"state" : "IN",
    "zip": "47633",
    "city": "Poseyville",
    "county": "Posey",
    "pop": 2384
  },
  {"state" : "IN",
    "zip": "47341",
    "city": "Fountain City",
    "county": "Wayne",
    "pop": 2382
  },
  {"state" : "IN",
    "zip": "47634",
    "city": "Richland",
    "county": "Spencer",
    "pop": 2358
  },
  {"state" : "IN",
    "zip": "47108",
    "city": "Campbellsburg",
    "county": "Washington",
    "pop": 2352
  },
  {"state" : "IN",
    "zip": "46070",
    "city": "Summitville",
    "county": "Madison",
    "pop": 2336
  },
  {"state" : "IN",
    "zip": "46216",
    "city": "Indianapolis",
    "county": "Marion",
    "pop": 2324
  },
  {"state" : "IN",
    "zip": "47977",
    "city": "Remington",
    "county": "Jasper",
    "pop": 2322
  },
  {"state" : "IN",
    "zip": "47841",
    "city": "Clay City",
    "county": "Clay",
    "pop": 2305
  },
  {"state" : "IN",
    "zip": "47227",
    "city": "Commiskey",
    "county": "Jennings",
    "pop": 2299
  },
  {"state" : "IN",
    "zip": "46747",
    "city": "Hudson",
    "county": "Steuben",
    "pop": 2292
  },
  {"state" : "IN",
    "zip": "47920",
    "city": "Battle Ground",
    "county": "Tippecanoe",
    "pop": 2260
  },
  {"state" : "IN",
    "zip": "47850",
    "city": "Farmersburg",
    "county": "Sullivan",
    "pop": 2239
  },
  {"state" : "IN",
    "zip": "46056",
    "city": "Markleville",
    "county": "Madison",
    "pop": 2238
  },
  {"state" : "IN",
    "zip": "47513",
    "city": "Birdseye",
    "county": "Dubois",
    "pop": 2222
  },
  {"state" : "IN",
    "zip": "47631",
    "city": "New Harmony",
    "county": "Posey",
    "pop": 2217
  },
  {"state" : "IN",
    "zip": "47273",
    "city": "Scipio",
    "county": "Jennings",
    "pop": 2210
  },
  {"state" : "IN",
    "zip": "47326",
    "city": "Bryant",
    "county": "Jay",
    "pop": 2195
  },
  {"state" : "IN",
    "zip": "47272",
    "city": "St. Paul",
    "county": "Decatur",
    "pop": 2185
  },
  {"state" : "IN",
    "zip": "47946",
    "city": "Francesville",
    "county": "Pulaski",
    "pop": 2170
  },
  {"state" : "IN",
    "zip": "47951",
    "city": "Kentland",
    "county": "Newton",
    "pop": 2168
  },
  {"state" : "IN",
    "zip": "46166",
    "city": "Paragon",
    "county": "Morgan",
    "pop": 2167
  },
  {"state" : "IN",
    "zip": "46784",
    "city": "Rome City",
    "county": "Noble",
    "pop": 2159
  },
  {"state" : "IN",
    "zip": "46149",
    "city": "Lizton",
    "county": "Hendricks",
    "pop": 2153
  },
  {"state" : "IN",
    "zip": "46745",
    "city": "Hoagland",
    "county": "Allen",
    "pop": 2146
  },
  {"state" : "IN",
    "zip": "46779",
    "city": "Pleasant Lake",
    "county": "Steuben",
    "pop": 2144
  },
  {"state" : "IN",
    "zip": "46978",
    "city": "Royal Center",
    "county": "Cass",
    "pop": 2135
  },
  {"state" : "IN",
    "zip": "46050",
    "city": "Kirklin",
    "county": "Clinton",
    "pop": 2127
  },
  {"state" : "IN",
    "zip": "46524",
    "city": "Etna Green",
    "county": "Kosciusko",
    "pop": 2124
  },
  {"state" : "IN",
    "zip": "46048",
    "city": "Ingalls",
    "county": "Madison",
    "pop": 2117
  },
  {"state" : "IN",
    "zip": "46974",
    "city": "Roann",
    "county": "Wabash",
    "pop": 2079
  },
  {"state" : "IN",
    "zip": "46702",
    "city": "Andrews",
    "county": "Huntington",
    "pop": 2074
  },
  {"state" : "IN",
    "zip": "47963",
    "city": "Morocco",
    "county": "Newton",
    "pop": 2057
  },
  {"state" : "IN",
    "zip": "46743",
    "city": "Harlan",
    "county": "Allen",
    "pop": 2050
  },
  {"state" : "IN",
    "zip": "47384",
    "city": "Shirley",
    "county": "Henry",
    "pop": 2044
  },
  {"state" : "IN",
    "zip": "47030",
    "city": "Metamora",
    "county": "Franklin",
    "pop": 2038
  },
  {"state" : "IN",
    "zip": "47928",
    "city": "Cayuga",
    "county": "Vermillion",
    "pop": 2036
  },
  {"state" : "IN",
    "zip": "46115",
    "city": "Carthage",
    "county": "Rush",
    "pop": 1967
  },
  {"state" : "IN",
    "zip": "47990",
    "city": "Waynetown",
    "county": "Montgomery",
    "pop": 1964
  },
  {"state" : "IN",
    "zip": "47971",
    "city": "Oxford",
    "county": "Benton",
    "pop": 1957
  },
  {"state" : "IN",
    "zip": "47527",
    "city": "Dubois",
    "county": "Dubois",
    "pop": 1935
  },
  {"state" : "IN",
    "zip": "47145",
    "city": "Milltown",
    "county": "Crawford",
    "pop": 1913
  },
  {"state" : "IN",
    "zip": "47957",
    "city": "Medaryville",
    "county": "Pulaski",
    "pop": 1908
  },
  {"state" : "IN",
    "zip": "46763",
    "city": "Laotto",
    "county": "Noble",
    "pop": 1881
  },
  {"state" : "IN",
    "zip": "46951",
    "city": "Macy",
    "county": "Miami",
    "pop": 1874
  },
  {"state" : "IN",
    "zip": "47615",
    "city": "Grandview",
    "county": "Spencer",
    "pop": 1832
  },
  {"state" : "IN",
    "zip": "47840",
    "city": "Centerpoint",
    "county": "Clay",
    "pop": 1831
  },
  {"state" : "IN",
    "zip": "47469",
    "city": "West Baden Springs",
    "county": "Orange",
    "pop": 1828
  },
  {"state" : "IN",
    "zip": "47393",
    "city": "Williamsburg",
    "county": "Wayne",
    "pop": 1825
  },
  {"state" : "IN",
    "zip": "46128",
    "city": "Fillmore",
    "county": "Putnam",
    "pop": 1824
  },
  {"state" : "IN",
    "zip": "46939",
    "city": "Kewanna",
    "county": "Fulton",
    "pop": 1819
  },
  {"state" : "IN",
    "zip": "47666",
    "city": "Patoka",
    "county": "Gibson",
    "pop": 1813
  },
  {"state" : "IN",
    "zip": "46105",
    "city": "Bainbridge",
    "county": "Putnam",
    "pop": 1794
  },
  {"state" : "IN",
    "zip": "46917",
    "city": "Camden",
    "county": "Carroll",
    "pop": 1781
  },
  {"state" : "IN",
    "zip": "47970",
    "city": "Otterbein",
    "county": "Benton",
    "pop": 1779
  },
  {"state" : "IN",
    "zip": "46171",
    "city": "Reelsville",
    "county": "Putnam",
    "pop": 1762
  },
  {"state" : "IN",
    "zip": "47619",
    "city": "Lynnville",
    "county": "Warrick",
    "pop": 1753
  },
  {"state" : "IN",
    "zip": "47940",
    "city": "Darlington",
    "county": "Montgomery",
    "pop": 1739
  },
  {"state" : "IN",
    "zip": "46914",
    "city": "Bunker Hill",
    "county": "Miami",
    "pop": 1729
  },
  {"state" : "IN",
    "zip": "47038",
    "city": "Patriot",
    "county": "Switzerland",
    "pop": 1716
  },
  {"state" : "IN",
    "zip": "46776",
    "city": "Orland",
    "county": "Steuben",
    "pop": 1715
  },
  {"state" : "IN",
    "zip": "46382",
    "city": "Union Mills",
    "county": "La Porte",
    "pop": 1713
  },
  {"state" : "IN",
    "zip": "46794",
    "city": "Wawaka",
    "county": "Noble",
    "pop": 1709
  },
  {"state" : "IN",
    "zip": "47260",
    "city": "Medora",
    "county": "Jackson",
    "pop": 1705
  },
  {"state" : "IN",
    "zip": "46785",
    "city": "Saint Joe",
    "county": "De Kalb",
    "pop": 1686
  },
  {"state" : "IN",
    "zip": "46986",
    "city": "Swayzee",
    "county": "Grant",
    "pop": 1683
  },
  {"state" : "IN",
    "zip": "46705",
    "city": "Ashley",
    "county": "De Kalb",
    "pop": 1682
  },
  {"state" : "IN",
    "zip": "47995",
    "city": "Wolcott",
    "county": "White",
    "pop": 1670
  },
  {"state" : "IN",
    "zip": "47023",
    "city": "Holton",
    "county": "Ripley",
    "pop": 1665
  },
  {"state" : "IN",
    "zip": "46186",
    "city": "Wilkinson",
    "county": "Hancock",
    "pop": 1652
  },
  {"state" : "IN",
    "zip": "47561",
    "city": "Oaktown",
    "county": "Knox",
    "pop": 1650
  },
  {"state" : "IN",
    "zip": "47848",
    "city": "Dugger",
    "county": "Sullivan",
    "pop": 1616
  },
  {"state" : "IN",
    "zip": "46991",
    "city": "Van Buren",
    "county": "Grant",
    "pop": 1614
  },
  {"state" : "IN",
    "zip": "47557",
    "city": "Monroe City",
    "county": "Knox",
    "pop": 1586
  },
  {"state" : "IN",
    "zip": "47431",
    "city": "Freedom",
    "county": "Owen",
    "pop": 1584
  },
  {"state" : "IN",
    "zip": "47470",
    "city": "Williams",
    "county": "Lawrence",
    "pop": 1580
  },
  {"state" : "IN",
    "zip": "46531",
    "city": "Grovertown",
    "county": "Starke",
    "pop": 1579
  },
  {"state" : "IN",
    "zip": "47922",
    "city": "Brook",
    "county": "Newton",
    "pop": 1570
  },
  {"state" : "IN",
    "zip": "47514",
    "city": "Branchville",
    "county": "Perry",
    "pop": 1556
  },
  {"state" : "IN",
    "zip": "47125",
    "city": "Hardinsburg",
    "county": "Washington",
    "pop": 1554
  },
  {"state" : "IN",
    "zip": "47141",
    "city": "Marysville",
    "county": "Clark",
    "pop": 1542
  },
  {"state" : "IN",
    "zip": "46532",
    "city": "Hamlet",
    "county": "Starke",
    "pop": 1531
  },
  {"state" : "IN",
    "zip": "46182",
    "city": "Waldron",
    "county": "Shelby",
    "pop": 1526
  },
  {"state" : "IN",
    "zip": "46165",
    "city": "North Salem",
    "county": "Hendricks",
    "pop": 1522
  },
  {"state" : "IN",
    "zip": "47166",
    "city": "Ramsey",
    "county": "Harrison",
    "pop": 1515
  },
  {"state" : "IN",
    "zip": "46798",
    "city": "Yoder",
    "county": "Allen",
    "pop": 1515
  },
  {"state" : "IN",
    "zip": "47468",
    "city": "Unionville",
    "county": "Monroe",
    "pop": 1510
  },
  {"state" : "IN",
    "zip": "47137",
    "city": "Leavenworth",
    "county": "Crawford",
    "pop": 1499
  },
  {"state" : "IN",
    "zip": "47649",
    "city": "Francisco",
    "county": "Gibson",
    "pop": 1499
  },
  {"state" : "IN",
    "zip": "47611",
    "city": "Chrisney",
    "county": "Spencer",
    "pop": 1489
  },
  {"state" : "IN",
    "zip": "47235",
    "city": "Freetown",
    "county": "Jackson",
    "pop": 1488
  },
  {"state" : "IN",
    "zip": "47948",
    "city": "Goodland",
    "county": "Newton",
    "pop": 1485
  },
  {"state" : "IN",
    "zip": "46911",
    "city": "Amboy",
    "county": "Miami",
    "pop": 1483
  },
  {"state" : "IN",
    "zip": "47926",
    "city": "Burnettsville",
    "county": "White",
    "pop": 1480
  },
  {"state" : "IN",
    "zip": "47380",
    "city": "Ridgeville",
    "county": "Randolph",
    "pop": 1476
  },
  {"state" : "IN",
    "zip": "47234",
    "city": "Flat Rock",
    "county": "Shelby",
    "pop": 1457
  },
  {"state" : "IN",
    "zip": "46076",
    "city": "Windfall",
    "county": "Tipton",
    "pop": 1440
  },
  {"state" : "IN",
    "zip": "47230",
    "city": "Deputy",
    "county": "Jefferson",
    "pop": 1439
  },
  {"state" : "IN",
    "zip": "46985",
    "city": "Star City",
    "county": "Pulaski",
    "pop": 1438
  },
  {"state" : "IN",
    "zip": "47020",
    "city": "Florence",
    "county": "Switzerland",
    "pop": 1432
  },
  {"state" : "IN",
    "zip": "47989",
    "city": "Waveland",
    "county": "Montgomery",
    "pop": 1430
  },
  {"state" : "IN",
    "zip": "47345",
    "city": "Greens Fork",
    "county": "Wayne",
    "pop": 1406
  },
  {"state" : "IN",
    "zip": "47941",
    "city": "Dayton",
    "county": "Tippecanoe",
    "pop": 1405
  },
  {"state" : "IN",
    "zip": "47862",
    "city": "Montezuma",
    "county": "Parke",
    "pop": 1390
  },
  {"state" : "IN",
    "zip": "46764",
    "city": "Larwill",
    "county": "Whitley",
    "pop": 1385
  },
  {"state" : "IN",
    "zip": "46760",
    "city": "Kimmell",
    "county": "Noble",
    "pop": 1381
  },
  {"state" : "IN",
    "zip": "47436",
    "city": "Heltonville",
    "county": "Lawrence",
    "pop": 1379
  },
  {"state" : "IN",
    "zip": "47992",
    "city": "Westpoint",
    "county": "Tippecanoe",
    "pop": 1357
  },
  {"state" : "IN",
    "zip": "47456",
    "city": "Quincy",
    "county": "Owen",
    "pop": 1352
  },
  {"state" : "IN",
    "zip": "47369",
    "city": "Pennville",
    "county": "Jay",
    "pop": 1320
  },
  {"state" : "IN",
    "zip": "47930",
    "city": "Clarks Hill",
    "county": "Tippecanoe",
    "pop": 1294
  },
  {"state" : "IN",
    "zip": "47637",
    "city": "Tennyson",
    "county": "Warrick",
    "pop": 1294
  },
  {"state" : "IN",
    "zip": "46926",
    "city": "Denver",
    "county": "Miami",
    "pop": 1293
  },
  {"state" : "IN",
    "zip": "47385",
    "city": "Spiceland",
    "county": "Henry",
    "pop": 1277
  },
  {"state" : "IN",
    "zip": "47443",
    "city": "Lyons",
    "county": "Greene",
    "pop": 1275
  },
  {"state" : "IN",
    "zip": "47147",
    "city": "Nabb",
    "county": "Clark",
    "pop": 1273
  },
  {"state" : "IN",
    "zip": "46057",
    "city": "Michigantown",
    "county": "Clinton",
    "pop": 1269
  },
  {"state" : "IN",
    "zip": "47360",
    "city": "Mooreland",
    "county": "Henry",
    "pop": 1259
  },
  {"state" : "IN",
    "zip": "46156",
    "city": "Milroy",
    "county": "Rush",
    "pop": 1253
  },
  {"state" : "IN",
    "zip": "47177",
    "city": "Underwood",
    "county": "Clark",
    "pop": 1241
  },
  {"state" : "IN",
    "zip": "47281",
    "city": "Vallonia",
    "county": "Jackson",
    "pop": 1237
  },
  {"state" : "IN",
    "zip": "46035",
    "city": "Colfax",
    "county": "Clinton",
    "pop": 1229
  },
  {"state" : "IN",
    "zip": "47564",
    "city": "Otwell",
    "county": "Pike",
    "pop": 1224
  },
  {"state" : "IN",
    "zip": "47577",
    "city": "Saint Meinrad",
    "county": "Spencer",
    "pop": 1211
  },
  {"state" : "IN",
    "zip": "47163",
    "city": "Otisco",
    "county": "Clark",
    "pop": 1210
  },
  {"state" : "IN",
    "zip": "47949",
    "city": "Hillsboro",
    "county": "Fountain",
    "pop": 1209
  },
  {"state" : "IN",
    "zip": "46346",
    "city": "Kingsford Heights",
    "county": "La Porte",
    "pop": 1208
  },
  {"state" : "IN",
    "zip": "47386",
    "city": "Springport",
    "county": "Henry",
    "pop": 1206
  },
  {"state" : "IN",
    "zip": "47264",
    "city": "Norman",
    "county": "Jackson",
    "pop": 1197
  },
  {"state" : "IN",
    "zip": "47541",
    "city": "Holland",
    "county": "Dubois",
    "pop": 1196
  },
  {"state" : "IN",
    "zip": "47847",
    "city": "Dana",
    "county": "Vermillion",
    "pop": 1187
  },
  {"state" : "IN",
    "zip": "47974",
    "city": "Perrysville",
    "county": "Vermillion",
    "pop": 1176
  },
  {"state" : "IN",
    "zip": "47529",
    "city": "Elnora",
    "county": "Daviess",
    "pop": 1173
  },
  {"state" : "IN",
    "zip": "46150",
    "city": "Manilla",
    "county": "Rush",
    "pop": 1147
  },
  {"state" : "IN",
    "zip": "47921",
    "city": "Boswell",
    "county": "Benton",
    "pop": 1140
  },
  {"state" : "IN",
    "zip": "47981",
    "city": "Romney",
    "county": "Tippecanoe",
    "pop": 1130
  },
  {"state" : "IN",
    "zip": "47451",
    "city": "Oolitic",
    "county": "Lawrence",
    "pop": 1111
  },
  {"state" : "IN",
    "zip": "46920",
    "city": "Cutler",
    "county": "Carroll",
    "pop": 1103
  },
  {"state" : "IN",
    "zip": "47516",
    "city": "Bruceville",
    "county": "Knox",
    "pop": 1100
  },
  {"state" : "IN",
    "zip": "47640",
    "city": "Hazleton",
    "county": "Gibson",
    "pop": 1099
  },
  {"state" : "IN",
    "zip": "47943",
    "city": "Fair Oaks",
    "county": "Jasper",
    "pop": 1096
  },
  {"state" : "IN",
    "zip": "46049",
    "city": "Kempton",
    "county": "Tipton",
    "pop": 1082
  },
  {"state" : "IN",
    "zip": "47354",
    "city": "Losantville",
    "county": "Randolph",
    "pop": 1075
  },
  {"state" : "IN",
    "zip": "46960",
    "city": "Monterey",
    "county": "Pulaski",
    "pop": 1062
  },
  {"state" : "IN",
    "zip": "47358",
    "city": "Modoc",
    "county": "Randolph",
    "pop": 1060
  },
  {"state" : "IN",
    "zip": "47832",
    "city": "Bloomingdale",
    "county": "Parke",
    "pop": 1059
  },
  {"state" : "IN",
    "zip": "47142",
    "city": "Mauckport",
    "county": "Harrison",
    "pop": 1049
  },
  {"state" : "IN",
    "zip": "46913",
    "city": "Bringhurst",
    "county": "Carroll",
    "pop": 1048
  },
  {"state" : "IN",
    "zip": "46730",
    "city": "Corunna",
    "county": "De Kalb",
    "pop": 1039
  },
  {"state" : "IN",
    "zip": "47175",
    "city": "Taswell",
    "county": "Crawford",
    "pop": 1033
  },
  {"state" : "IN",
    "zip": "46348",
    "city": "La Crosse",
    "county": "La Porte",
    "pop": 1031
  },
  {"state" : "IN",
    "zip": "47968",
    "city": "New Ross",
    "county": "Montgomery",
    "pop": 1030
  },
  {"state" : "IN",
    "zip": "47859",
    "city": "Marshall",
    "county": "Parke",
    "pop": 1027
  },
  {"state" : "IN",
    "zip": "47223",
    "city": "Butlerville",
    "county": "Jennings",
    "pop": 1024
  },
  {"state" : "IN",
    "zip": "47955",
    "city": "Linden",
    "county": "Montgomery",
    "pop": 1016
  },
  {"state" : "IN",
    "zip": "47837",
    "city": "Carbon",
    "county": "Clay",
    "pop": 1008
  },
  {"state" : "IN",
    "zip": "47980",
    "city": "Reynolds",
    "county": "White",
    "pop": 1005
  },
  {"state" : "IN",
    "zip": "47280",
    "city": "Taylorsville",
    "county": "Bartholomew",
    "pop": 979
  },
  {"state" : "IN",
    "zip": "46180",
    "city": "Stilesville",
    "county": "Hendricks",
    "pop": 976
  },
  {"state" : "IN",
    "zip": "47991",
    "city": "West Lebanon",
    "county": "Warren",
    "pop": 975
  },
  {"state" : "IN",
    "zip": "46941",
    "city": "Lagro",
    "county": "Wabash",
    "pop": 970
  },
  {"state" : "IN",
    "zip": "46988",
    "city": "Twelve Mile",
    "county": "Cass",
    "pop": 967
  },
  {"state" : "IN",
    "zip": "47575",
    "city": "Saint Anthony",
    "county": "Dubois",
    "pop": 955
  },
  {"state" : "IN",
    "zip": "47531",
    "city": "Evanston",
    "county": "Spencer",
    "pop": 945
  },
  {"state" : "IN",
    "zip": "47135",
    "city": "Laconia",
    "county": "Harrison",
    "pop": 938
  },
  {"state" : "IN",
    "zip": "47950",
    "city": "Idaville",
    "county": "White",
    "pop": 921
  },
  {"state" : "IN",
    "zip": "47551",
    "city": "Leopold",
    "county": "Perry",
    "pop": 914
  },
  {"state" : "IN",
    "zip": "46104",
    "city": "Arlington",
    "county": "Rush",
    "pop": 910
  },
  {"state" : "IN",
    "zip": "47597",
    "city": "Wheatland",
    "county": "Knox",
    "pop": 904
  },
  {"state" : "IN",
    "zip": "47537",
    "city": "Gentryville",
    "county": "Spencer",
    "pop": 896
  },
  {"state" : "IN",
    "zip": "47003",
    "city": "West College Corner",
    "county": "Union",
    "pop": 890
  },
  {"state" : "IN",
    "zip": "46987",
    "city": "Sweetser",
    "county": "Grant",
    "pop": 884
  },
  {"state" : "IN",
    "zip": "47036",
    "city": "Oldenburg",
    "county": "Franklin",
    "pop": 882
  },
  {"state" : "IN",
    "zip": "47515",
    "city": "Bristow",
    "county": "Perry",
    "pop": 880
  },
  {"state" : "IN",
    "zip": "46374",
    "city": "San Pierre",
    "county": "Starke",
    "pop": 873
  },
  {"state" : "IN",
    "zip": "46791",
    "city": "Uniondale",
    "county": "Wells",
    "pop": 865
  },
  {"state" : "IN",
    "zip": "47352",
    "city": "Lewisville",
    "county": "Henry",
    "pop": 860
  },
  {"state" : "IN",
    "zip": "47231",
    "city": "Dupont",
    "county": "Jefferson",
    "pop": 858
  },
  {"state" : "IN",
    "zip": "47519",
    "city": "Cannelburg",
    "county": "Daviess",
    "pop": 847
  },
  {"state" : "IN",
    "zip": "46959",
    "city": "Miami",
    "county": "Miami",
    "pop": 838
  },
  {"state" : "IN",
    "zip": "46570",
    "city": "Tippecanoe",
    "county": "Marshall",
    "pop": 833
  },
  {"state" : "IN",
    "zip": "46133",
    "city": "Glenwood",
    "county": "Fayette",
    "pop": 833
  },
  {"state" : "IN",
    "zip": "47568",
    "city": "Plainville",
    "county": "Daviess",
    "pop": 829
  },
  {"state" : "IN",
    "zip": "46117",
    "city": "Charlottesville",
    "county": "Hancock",
    "pop": 828
  },
  {"state" : "IN",
    "zip": "47357",
    "city": "Milton",
    "county": "Wayne",
    "pop": 822
  },
  {"state" : "IN",
    "zip": "47162",
    "city": "New Washington",
    "county": "Clark",
    "pop": 801
  },
  {"state" : "IN",
    "zip": "47585",
    "city": "Stendal",
    "county": "Pike",
    "pop": 800
  },
  {"state" : "IN",
    "zip": "47016",
    "city": "Cedar Grove",
    "county": "Franklin",
    "pop": 796
  },
  {"state" : "IN",
    "zip": "47011",
    "city": "Bennington",
    "county": "Switzerland",
    "pop": 788
  },
  {"state" : "IN",
    "zip": "47833",
    "city": "Bowling Green",
    "county": "Clay",
    "pop": 761
  },
  {"state" : "IN",
    "zip": "46731",
    "city": "Craigville",
    "county": "Wells",
    "pop": 759
  },
  {"state" : "IN",
    "zip": "47535",
    "city": "Freelandville",
    "county": "Knox",
    "pop": 758
  },
  {"state" : "IN",
    "zip": "46365",
    "city": "Mill Creek",
    "county": "La Porte",
    "pop": 755
  },
  {"state" : "IN",
    "zip": "47335",
    "city": "Dublin",
    "county": "Wayne",
    "pop": 753
  },
  {"state" : "IN",
    "zip": "46340",
    "city": "Hanna",
    "county": "La Porte",
    "pop": 742
  },
  {"state" : "IN",
    "zip": "46990",
    "city": "Urbana",
    "county": "Wabash",
    "pop": 741
  },
  {"state" : "IN",
    "zip": "47120",
    "city": "Fredericksburg",
    "county": "Washington",
    "pop": 741
  },
  {"state" : "IN",
    "zip": "46766",
    "city": "Liberty Center",
    "county": "Wells",
    "pop": 737
  },
  {"state" : "IN",
    "zip": "47244",
    "city": "Hartsville",
    "county": "Bartholomew",
    "pop": 734
  },
  {"state" : "IN",
    "zip": "47387",
    "city": "Straughn",
    "county": "Henry",
    "pop": 730
  },
  {"state" : "IN",
    "zip": "47942",
    "city": "Earl Park",
    "county": "Benton",
    "pop": 728
  },
  {"state" : "IN",
    "zip": "46781",
    "city": "Poneto",
    "county": "Wells",
    "pop": 728
  },
  {"state" : "IN",
    "zip": "47858",
    "city": "Lewis",
    "county": "Vigo",
    "pop": 724
  },
  {"state" : "IN",
    "zip": "47612",
    "city": "Cynthiana",
    "county": "Posey",
    "pop": 715
  },
  {"state" : "IN",
    "zip": "47578",
    "city": "Sandborn",
    "county": "Knox",
    "pop": 710
  },
  {"state" : "IN",
    "zip": "46915",
    "city": "Burlington",
    "county": "Carroll",
    "pop": 694
  },
  {"state" : "IN",
    "zip": "47521",
    "city": "Celestine",
    "county": "Dubois",
    "pop": 692
  },
  {"state" : "IN",
    "zip": "47453",
    "city": "Owensburg",
    "county": "Greene",
    "pop": 683
  },
  {"state" : "IN",
    "zip": "47116",
    "city": "Eckerty",
    "county": "Crawford",
    "pop": 681
  },
  {"state" : "IN",
    "zip": "47967",
    "city": "New Richmond",
    "county": "Montgomery",
    "pop": 680
  },
  {"state" : "IN",
    "zip": "47929",
    "city": "Chalmers",
    "county": "White",
    "pop": 673
  },
  {"state" : "IN",
    "zip": "47975",
    "city": "Pine Village",
    "county": "Warren",
    "pop": 664
  },
  {"state" : "IN",
    "zip": "47325",
    "city": "Brownsville",
    "county": "Union",
    "pop": 663
  },
  {"state" : "IN",
    "zip": "47861",
    "city": "Merom",
    "county": "Sullivan",
    "pop": 663
  },
  {"state" : "IN",
    "zip": "47427",
    "city": "Coal City",
    "county": "Owen",
    "pop": 662
  },
  {"state" : "IN",
    "zip": "46175",
    "city": "Russellville",
    "county": "Putnam",
    "pop": 646
  },
  {"state" : "IN",
    "zip": "47588",
    "city": "Troy",
    "county": "Spencer",
    "pop": 615
  },
  {"state" : "IN",
    "zip": "47866",
    "city": "Pimento",
    "county": "Vigo",
    "pop": 613
  },
  {"state" : "IN",
    "zip": "47854",
    "city": "Hillsdale",
    "county": "Vermillion",
    "pop": 612
  },
  {"state" : "IN",
    "zip": "47524",
    "city": "Decker",
    "county": "Knox",
    "pop": 612
  },
  {"state" : "IN",
    "zip": "47965",
    "city": "New Market",
    "county": "Montgomery",
    "pop": 599
  },
  {"state" : "IN",
    "zip": "46957",
    "city": "Matthews",
    "county": "Grant",
    "pop": 592
  },
  {"state" : "IN",
    "zip": "46110",
    "city": "Boggstown",
    "county": "Shelby",
    "pop": 583
  },
  {"state" : "IN",
    "zip": "46950",
    "city": "Lucerne",
    "county": "Cass",
    "pop": 566
  },
  {"state" : "IN",
    "zip": "46063",
    "city": "Orestes",
    "county": "Madison",
    "pop": 565
  },
  {"state" : "IN",
    "zip": "47550",
    "city": "Lamar",
    "county": "Spencer",
    "pop": 561
  },
  {"state" : "IN",
    "zip": "47351",
    "city": "Kennard",
    "county": "Henry",
    "pop": 540
  },
  {"state" : "IN",
    "zip": "47846",
    "city": "Cory",
    "county": "Clay",
    "pop": 532
  },
  {"state" : "IN",
    "zip": "47270",
    "city": "Paris Crossing",
    "county": "Jennings",
    "pop": 530
  },
  {"state" : "IN",
    "zip": "47855",
    "city": "Hymera",
    "county": "Sullivan",
    "pop": 526
  },
  {"state" : "IN",
    "zip": "47224",
    "city": "Canaan",
    "county": "Jefferson",
    "pop": 520
  },
  {"state" : "IN",
    "zip": "47465",
    "city": "Switz City",
    "county": "Greene",
    "pop": 520
  },
  {"state" : "IN",
    "zip": "46301",
    "city": "Beverly Shores",
    "county": "Porter",
    "pop": 516
  },
  {"state" : "IN",
    "zip": "46759",
    "city": "Keystone",
    "county": "Wells",
    "pop": 508
  },
  {"state" : "IN",
    "zip": "46039",
    "city": "Forest",
    "county": "Clinton",
    "pop": 508
  },
  {"state" : "IN",
    "zip": "47528",
    "city": "Edwardsport",
    "county": "Knox",
    "pop": 504
  },
  {"state" : "IN",
    "zip": "47849",
    "city": "Fairbanks",
    "county": "Sullivan",
    "pop": 502
  },
  {"state" : "IN",
    "zip": "47339",
    "city": "Economy",
    "county": "Wayne",
    "pop": 497
  },
  {"state" : "IN",
    "zip": "47917",
    "city": "Ambia",
    "county": "Benton",
    "pop": 492
  },
  {"state" : "IN",
    "zip": "47017",
    "city": "Cross Plains",
    "county": "Ripley",
    "pop": 481
  },
  {"state" : "IN",
    "zip": "46958",
    "city": "Mexico",
    "county": "Miami",
    "pop": 458
  },
  {"state" : "IN",
    "zip": "47708",
    "city": "Evansville",
    "county": "Vanderburgh",
    "pop": 445
  },
  {"state" : "IN",
    "zip": "47420",
    "city": "Avoca",
    "county": "Lawrence",
    "pop": 439
  },
  {"state" : "IN",
    "zip": "47522",
    "city": "Crane",
    "county": "Martin",
    "pop": 437
  },
  {"state" : "IN",
    "zip": "47860",
    "city": "Mecca",
    "county": "Parke",
    "pop": 425
  },
  {"state" : "IN",
    "zip": "46537",
    "city": "Lapaz",
    "county": "Marshall",
    "pop": 425
  },
  {"state" : "IN",
    "zip": "47857",
    "city": "Knightsville",
    "county": "Clay",
    "pop": 420
  },
  {"state" : "IN",
    "zip": "47110",
    "city": "Central",
    "county": "Harrison",
    "pop": 417
  },
  {"state" : "IN",
    "zip": "46146",
    "city": "Homer",
    "county": "Rush",
    "pop": 416
  },
  {"state" : "IN",
    "zip": "47590",
    "city": "Velpen",
    "county": "Pike",
    "pop": 413
  },
  {"state" : "IN",
    "zip": "47580",
    "city": "Schnellville",
    "county": "Dubois",
    "pop": 406
  },
  {"state" : "IN",
    "zip": "47449",
    "city": "Newberry",
    "county": "Greene",
    "pop": 400
  },
  {"state" : "IN",
    "zip": "47966",
    "city": "Newport",
    "county": "Vermillion",
    "pop": 359
  },
  {"state" : "IN",
    "zip": "47876",
    "city": "Saint Mary Of The Woods",
    "county": "Vigo",
    "pop": 348
  },
  {"state" : "IN",
    "zip": "47576",
    "city": "Saint Croix",
    "county": "Perry",
    "pop": 341
  },
  {"state" : "IN",
    "zip": "47388",
    "city": "Sulphur Springs",
    "county": "Henry",
    "pop": 335
  },
  {"state" : "IN",
    "zip": "46377",
    "city": "Shelby",
    "county": "Lake",
    "pop": 332
  },
  {"state" : "IN",
    "zip": "47881",
    "city": "Staunton",
    "county": "Clay",
    "pop": 329
  },
  {"state" : "IN",
    "zip": "47114",
    "city": "Crandall",
    "county": "Harrison",
    "pop": 328
  },
  {"state" : "IN",
    "zip": "47871",
    "city": "Riley",
    "county": "Vigo",
    "pop": 321
  },
  {"state" : "IN",
    "zip": "46162",
    "city": "Needham",
    "county": "Johnson",
    "pop": 314
  },
  {"state" : "IN",
    "zip": "47994",
    "city": "Wingate",
    "county": "Montgomery",
    "pop": 309
  },
  {"state" : "IN",
    "zip": "47983",
    "city": "Stockwell",
    "county": "Tippecanoe",
    "pop": 303
  },
  {"state" : "IN",
    "zip": "46393",
    "city": "Wheeler",
    "county": "Porter",
    "pop": 296
  },
  {"state" : "IN",
    "zip": "47863",
    "city": "New Goshen",
    "county": "Vigo",
    "pop": 294
  },
  {"state" : "IN",
    "zip": "47282",
    "city": "Vernon",
    "county": "Jennings",
    "pop": 293
  },
  {"state" : "IN",
    "zip": "46127",
    "city": "Falmouth",
    "county": "Rush",
    "pop": 287
  },
  {"state" : "IN",
    "zip": "47525",
    "city": "Derby",
    "county": "Perry",
    "pop": 281
  },
  {"state" : "IN",
    "zip": "47552",
    "city": "Lincoln City",
    "county": "Spencer",
    "pop": 270
  },
  {"state" : "IN",
    "zip": "47616",
    "city": "Griffin",
    "county": "Posey",
    "pop": 265
  },
  {"state" : "IN",
    "zip": "47226",
    "city": "Clifford",
    "county": "Bartholomew",
    "pop": 260
  },
  {"state" : "IN",
    "zip": "47382",
    "city": "Saratoga",
    "county": "Randolph",
    "pop": 255
  },
  {"state" : "IN",
    "zip": "47263",
    "city": "New Point",
    "county": "Decatur",
    "pop": 255
  },
  {"state" : "IN",
    "zip": "47035",
    "city": "New Trenton",
    "county": "Franklin",
    "pop": 246
  },
  {"state" : "IN",
    "zip": "46376",
    "city": "Schneider",
    "county": "Lake",
    "pop": 243
  },
  {"state" : "IN",
    "zip": "47683",
    "city": "Somerville",
    "county": "Gibson",
    "pop": 235
  },
  {"state" : "IN",
    "zip": "46799",
    "city": "Zanesville",
    "county": "Allen",
    "pop": 227
  },
  {"state" : "IN",
    "zip": "46998",
    "city": "Young America",
    "county": "Cass",
    "pop": 226
  },
  {"state" : "IN",
    "zip": "46943",
    "city": "Laketon",
    "county": "Wabash",
    "pop": 225
  },
  {"state" : "IN",
    "zip": "47010",
    "city": "Bath",
    "county": "Franklin",
    "pop": 220
  },
  {"state" : "IN",
    "zip": "47361",
    "city": "Mount Summit",
    "county": "Henry",
    "pop": 215
  },
  {"state" : "IN",
    "zip": "47574",
    "city": "Rome",
    "county": "Perry",
    "pop": 213
  },
  {"state" : "IN",
    "zip": "47464",
    "city": "Stinesville",
    "county": "Monroe",
    "pop": 212
  },
  {"state" : "IN",
    "zip": "46111",
    "city": "Brooklyn",
    "county": "Morgan",
    "pop": 196
  },
  {"state" : "IN",
    "zip": "47247",
    "city": "Jonesville",
    "county": "Bartholomew",
    "pop": 194
  },
  {"state" : "IN",
    "zip": "47457",
    "city": "Scotland",
    "county": "Greene",
    "pop": 192
  },
  {"state" : "IN",
    "zip": "46984",
    "city": "Somerset",
    "county": "Wabash",
    "pop": 188
  },
  {"state" : "IN",
    "zip": "46931",
    "city": "Fulton",
    "county": "Fulton",
    "pop": 187
  },
  {"state" : "IN",
    "zip": "46290",
    "city": "Indianapolis",
    "county": "Hamilton",
    "pop": 187
  },
  {"state" : "IN",
    "zip": "47884",
    "city": "Universal",
    "county": "Vermillion",
    "pop": 185
  },
  {"state" : "IN",
    "zip": "46381",
    "city": "Thayer",
    "county": "Newton",
    "pop": 176
  },
  {"state" : "IN",
    "zip": "47982",
    "city": "State Line",
    "county": "Warren",
    "pop": 173
  },
  {"state" : "IN",
    "zip": "46345",
    "city": "Kingsbury",
    "county": "La Porte",
    "pop": 170
  },
  {"state" : "IN",
    "zip": "46961",
    "city": "New Waverly",
    "county": "Cass",
    "pop": 169
  },
  {"state" : "IN",
    "zip": "47467",
    "city": "Tunnelton",
    "county": "Lawrence",
    "pop": 167
  },
  {"state" : "IN",
    "zip": "47924",
    "city": "Buck Creek",
    "county": "Tippecanoe",
    "pop": 162
  },
  {"state" : "IN",
    "zip": "46155",
    "city": "Mays",
    "county": "Rush",
    "pop": 162
  },
  {"state" : "IN",
    "zip": "46103",
    "city": "Amo",
    "county": "Hendricks",
    "pop": 162
  },
  {"state" : "IN",
    "zip": "47437",
    "city": "Huron",
    "county": "Lawrence",
    "pop": 155
  },
  {"state" : "IN",
    "zip": "47324",
    "city": "Boston",
    "county": "Wayne",
    "pop": 149
  },
  {"state" : "IN",
    "zip": "46968",
    "city": "Ora",
    "county": "Starke",
    "pop": 142
  },
  {"state" : "IN",
    "zip": "47958",
    "city": "Mellott",
    "county": "Fountain",
    "pop": 140
  },
  {"state" : "IN",
    "zip": "47584",
    "city": "Spurgeon",
    "county": "Pike",
    "pop": 139
  },
  {"state" : "IN",
    "zip": "47337",
    "city": "Dunreith",
    "county": "Henry",
    "pop": 138
  },
  {"state" : "IN",
    "zip": "47034",
    "city": "Napoleon",
    "county": "Ripley",
    "pop": 135
  },
  {"state" : "IN",
    "zip": "47997",
    "city": "Yeoman",
    "county": "Carroll",
    "pop": 134
  },
  {"state" : "IN",
    "zip": "47925",
    "city": "Buffalo",
    "county": "White",
    "pop": 133
  },
  {"state" : "IN",
    "zip": "46144",
    "city": "Gwynneville",
    "county": "Shelby",
    "pop": 133
  },
  {"state" : "IN",
    "zip": "46595",
    "city": "Wyatt",
    "county": "St Joseph",
    "pop": 133
  },
  {"state" : "IN",
    "zip": "46930",
    "city": "Fowlerton",
    "county": "Grant",
    "pop": 126
  },
  {"state" : "IN",
    "zip": "47344",
    "city": "Greensboro",
    "county": "Henry",
    "pop": 124
  },
  {"state" : "IN",
    "zip": "47869",
    "city": "Prairie Creek",
    "county": "Vigo",
    "pop": 124
  },
  {"state" : "IN",
    "zip": "47381",
    "city": "Salamonia",
    "county": "Jay",
    "pop": 122
  },
  {"state" : "IN",
    "zip": "47123",
    "city": "Grantsburg",
    "county": "Crawford",
    "pop": 122
  },
  {"state" : "IN",
    "zip": "47853",
    "city": "Harmony",
    "county": "Clay",
    "pop": 121
  },
  {"state" : "IN",
    "zip": "47160",
    "city": "New Middletown",
    "county": "Harrison",
    "pop": 113
  },
  {"state" : "IN",
    "zip": "46508",
    "city": "Burket",
    "county": "Kosciusko",
    "pop": 113
  },
  {"state" : "IN",
    "zip": "47964",
    "city": "Mount Ayr",
    "county": "Newton",
    "pop": 110
  },
  {"state" : "IN",
    "zip": "47969",
    "city": "Newtown",
    "county": "Fountain",
    "pop": 109
  },
  {"state" : "IN",
    "zip": "46967",
    "city": "Onward",
    "county": "Cass",
    "pop": 97
  },
  {"state" : "IN",
    "zip": "47654",
    "city": "Mackey",
    "county": "Gibson",
    "pop": 92
  },
  {"state" : "IN",
    "zip": "46379",
    "city": "Sumava Resorts",
    "county": "Newton",
    "pop": 81
  },
  {"state" : "IN",
    "zip": "47880",
    "city": "Shepardsville",
    "county": "Vigo",
    "pop": 78
  },
  {"state" : "IN",
    "zip": "47455",
    "city": "Patricksburg",
    "county": "Owen",
    "pop": 76
  },
  {"state" : "IN",
    "zip": "46771",
    "city": "Mongo",
    "county": "Lagrange",
    "pop": 72
  },
  {"state" : "IN",
    "zip": "47596",
    "city": "Westphalia",
    "county": "Knox",
    "pop": 71
  },
  {"state" : "IN",
    "zip": "47458",
    "city": "Smithville",
    "county": "Monroe",
    "pop": 58
  },
  {"state" : "IN",
    "zip": "46502",
    "city": "Atwood",
    "county": "Kosciusko",
    "pop": 58
  },
  {"state" : "IN",
    "zip": "47367",
    "city": "Oakville",
    "county": "Delaware",
    "pop": 57
  },
  {"state" : "IN",
    "zip": "46047",
    "city": "Hobbs",
    "county": "Tipton",
    "pop": 56
  },
  {"state" : "IN",
    "zip": "47865",
    "city": "Paxton",
    "county": "Sullivan",
    "pop": 55
  },
  {"state" : "IN",
    "zip": "46125",
    "city": "Eminence",
    "county": "Morgan",
    "pop": 55
  },
  {"state" : "IN",
    "zip": "47916",
    "city": "Alamo",
    "county": "Montgomery",
    "pop": 43
  },
  {"state" : "IN",
    "zip": "46786",
    "city": "South Milford",
    "county": "Lagrange",
    "pop": 39
  },
  {"state" : "IN",
    "zip": "46045",
    "city": "Goldsmith",
    "county": "Tipton",
    "pop": 39
  },
  {"state" : "IN",
    "zip": "46704",
    "city": "Arcola",
    "county": "Allen",
    "pop": 38
  },
  {"state" : "IN",
    "zip": "46946",
    "city": "Liberty Mills",
    "county": "Wabash",
    "pop": 34
  },
  {"state" : "IN",
    "zip": "46922",
    "city": "Delong",
    "county": "Fulton",
    "pop": 31
  },
  {"state" : "IN",
    "zip": "46183",
    "city": "West Newton",
    "county": "Marion",
    "pop": 15
  },
  {"state" : "IN",
    "zip": "47836",
    "city": "Bridgeton",
    "county": "Parke",
    "pop": 0
  },
  {"state" : "IN",
    "zip": "47907",
    "city": "West Lafayette",
    "county": "Tippecanoe",
    "pop": 0
  },
  {"state" : "IN",
    "zip": "47104",
    "city": "Bethlehem",
    "county": "Clark",
    "pop": 0
  },
  {"state" : "IN",
    "zip": "47536",
    "city": "Fulda",
    "county": "Spencer",
    "pop": 0
  },
  {"state" : "IN",
    "zip": "47434",
    "city": "Harrodsburg",
    "county": "Monroe",
    "pop": 0
  }
]